{"All Other Diseases":[{"age":0,"percentage":0.0544638},{"age":1,"percentage":0.1935600},{"age":2,"percentage":0.1697612},{"age":3,"percentage":0.1577934},{"age":4,"percentage":0.1555430},{"age":5,"percentage":0.1542415},{"age":6,"percentage":0.1578344},{"age":7,"percentage":0.1611033},{"age":8,"percentage":0.1574069},{"age":9,"percentage":0.1610736},{"age":10,"percentage":0.1688368},{"age":11,"percentage":0.1638758},{"age":12,"percentage":0.1575906},{"age":13,"percentage":0.1384254},{"age":14,"percentage":0.1191299},{"age":15,"percentage":0.1014189},{"age":16,"percentage":0.0775542},{"age":17,"percentage":0.0691204},{"age":18,"percentage":0.0623221},{"age":19,"percentage":0.0642809},{"age":20,"percentage":0.0676607},{"age":21,"percentage":0.0687447},{"age":22,"percentage":0.0718915},{"age":23,"percentage":0.0737990},{"age":24,"percentage":0.0787499},{"age":25,"percentage":0.0807964},{"age":26,"percentage":0.0832175},{"age":27,"percentage":0.0876682},{"age":28,"percentage":0.0918098},{"age":29,"percentage":0.0936132},{"age":30,"percentage":0.0955857},{"age":31,"percentage":0.0995615},{"age":32,"percentage":0.1020376},{"age":33,"percentage":0.1036059},{"age":34,"percentage":0.1060097},{"age":35,"percentage":0.1069081},{"age":36,"percentage":0.1103163},{"age":37,"percentage":0.1109795},{"age":38,"percentage":0.1112646},{"age":39,"percentage":0.1138987},{"age":40,"percentage":0.1125044},{"age":41,"percentage":0.1137414},{"age":42,"percentage":0.1145099},{"age":43,"percentage":0.1141790},{"age":44,"percentage":0.1139491},{"age":45,"percentage":0.1126242},{"age":46,"percentage":0.1131152},{"age":47,"percentage":0.1114721},{"age":48,"percentage":0.1114179},{"age":49,"percentage":0.1091862},{"age":50,"percentage":0.1078912},{"age":51,"percentage":0.1059765},{"age":52,"percentage":0.1043826},{"age":53,"percentage":0.1031756},{"age":54,"percentage":0.1013721},{"age":55,"percentage":0.0992854},{"age":56,"percentage":0.0983947},{"age":57,"percentage":0.0966386},{"age":58,"percentage":0.0954519},{"age":59,"percentage":0.0938899},{"age":60,"percentage":0.0927452},{"age":61,"percentage":0.0914762},{"age":62,"percentage":0.0913470},{"age":63,"percentage":0.0912424},{"age":64,"percentage":0.0904863},{"age":65,"percentage":0.0901711},{"age":66,"percentage":0.0907545},{"age":67,"percentage":0.0909470},{"age":68,"percentage":0.0910234},{"age":69,"percentage":0.0920837},{"age":70,"percentage":0.0929119},{"age":71,"percentage":0.0943973},{"age":72,"percentage":0.0963063},{"age":73,"percentage":0.0984408},{"age":74,"percentage":0.1010606},{"age":75,"percentage":0.1030254},{"age":76,"percentage":0.1068419},{"age":77,"percentage":0.1098975},{"age":78,"percentage":0.1131444},{"age":79,"percentage":0.1156677},{"age":80,"percentage":0.1186674},{"age":81,"percentage":0.1226855},{"age":82,"percentage":0.1261892},{"age":83,"percentage":0.1299067},{"age":84,"percentage":0.1332932},{"age":85,"percentage":0.1371248},{"age":86,"percentage":0.1403446},{"age":87,"percentage":0.1444185},{"age":88,"percentage":0.1477672},{"age":89,"percentage":0.1511551},{"age":90,"percentage":0.1527562},{"age":91,"percentage":0.1558103},{"age":92,"percentage":0.1585172},{"age":93,"percentage":0.1607260},{"age":94,"percentage":0.1631739},{"age":95,"percentage":0.1645463},{"age":96,"percentage":0.1663549},{"age":97,"percentage":0.1687726},{"age":98,"percentage":0.1695005},{"age":99,"percentage":0.1702353},{"age":100,"percentage":0.1668979},{"age":101,"percentage":0.1663617},{"age":102,"percentage":0.1665540},{"age":103,"percentage":0.1664824},{"age":104,"percentage":0.1641886},{"age":105,"percentage":0.1624423},{"age":106,"percentage":0.1558480},{"age":107,"percentage":0.1516335},{"age":108,"percentage":0.1620909},{"age":109,"percentage":0.1550607},{"age":110,"percentage":0.1304627},{"age":111,"percentage":0.1644172},{"age":112,"percentage":0.1359026},{"age":113,"percentage":0.1145511},{"age":114,"percentage":0.1097046},{"age":115,"percentage":0.0982659},{"age":116,"percentage":0.1290323},{"age":117,"percentage":0.1111111},{"age":118,"percentage":0.0967742},{"age":119,"percentage":0.2051282},{"age":120,"percentage":0.0465116}],"All Other External Causes":[{"age":0,"percentage":0.0197775},{"age":1,"percentage":0.1750305},{"age":2,"percentage":0.2733824},{"age":3,"percentage":0.2776053},{"age":4,"percentage":0.2576246},{"age":5,"percentage":0.2259675},{"age":6,"percentage":0.2086062},{"age":7,"percentage":0.2092410},{"age":8,"percentage":0.2118035},{"age":9,"percentage":0.2149996},{"age":10,"percentage":0.2160893},{"age":11,"percentage":0.2198333},{"age":12,"percentage":0.2182456},{"age":13,"percentage":0.2194099},{"age":14,"percentage":0.2054861},{"age":15,"percentage":0.1855369},{"age":16,"percentage":0.1516676},{"age":17,"percentage":0.1442474},{"age":18,"percentage":0.1431739},{"age":19,"percentage":0.1498558},{"age":20,"percentage":0.1546567},{"age":21,"percentage":0.1550627},{"age":22,"percentage":0.1596505},{"age":23,"percentage":0.1631742},{"age":24,"percentage":0.1651140},{"age":25,"percentage":0.1667292},{"age":26,"percentage":0.1673422},{"age":27,"percentage":0.1641660},{"age":28,"percentage":0.1620748},{"age":29,"percentage":0.1587166},{"age":30,"percentage":0.1563277},{"age":31,"percentage":0.1506405},{"age":32,"percentage":0.1465540},{"age":33,"percentage":0.1416549},{"age":34,"percentage":0.1369099},{"age":35,"percentage":0.1324272},{"age":36,"percentage":0.1260752},{"age":37,"percentage":0.1216166},{"age":38,"percentage":0.1163663},{"age":39,"percentage":0.1112305},{"age":40,"percentage":0.1057365},{"age":41,"percentage":0.1008571},{"age":42,"percentage":0.0943024},{"age":43,"percentage":0.0892314},{"age":44,"percentage":0.0840910},{"age":45,"percentage":0.0786361},{"age":46,"percentage":0.0734416},{"age":47,"percentage":0.0681058},{"age":48,"percentage":0.0631301},{"age":49,"percentage":0.0579539},{"age":50,"percentage":0.0532112},{"age":51,"percentage":0.0487707},{"age":52,"percentage":0.0447199},{"age":53,"percentage":0.0407187},{"age":54,"percentage":0.0370550},{"age":55,"percentage":0.0340202},{"age":56,"percentage":0.0311485},{"age":57,"percentage":0.0286253},{"age":58,"percentage":0.0260678},{"age":59,"percentage":0.0238263},{"age":60,"percentage":0.0222646},{"age":61,"percentage":0.0205423},{"age":62,"percentage":0.0192138},{"age":63,"percentage":0.0178811},{"age":64,"percentage":0.0165769},{"age":65,"percentage":0.0158176},{"age":66,"percentage":0.0149596},{"age":67,"percentage":0.0146188},{"age":68,"percentage":0.0140474},{"age":69,"percentage":0.0136947},{"age":70,"percentage":0.0132192},{"age":71,"percentage":0.0130566},{"age":72,"percentage":0.0130794},{"age":73,"percentage":0.0131582},{"age":74,"percentage":0.0131865},{"age":75,"percentage":0.0134646},{"age":76,"percentage":0.0135795},{"age":77,"percentage":0.0138448},{"age":78,"percentage":0.0142768},{"age":79,"percentage":0.0147352},{"age":80,"percentage":0.0150771},{"age":81,"percentage":0.0154485},{"age":82,"percentage":0.0158833},{"age":83,"percentage":0.0166220},{"age":84,"percentage":0.0171021},{"age":85,"percentage":0.0174759},{"age":86,"percentage":0.0178001},{"age":87,"percentage":0.0183133},{"age":88,"percentage":0.0185965},{"age":89,"percentage":0.0187181},{"age":90,"percentage":0.0190742},{"age":91,"percentage":0.0192859},{"age":92,"percentage":0.0194730},{"age":93,"percentage":0.0196080},{"age":94,"percentage":0.0197183},{"age":95,"percentage":0.0196019},{"age":96,"percentage":0.0190503},{"age":97,"percentage":0.0195309},{"age":98,"percentage":0.0193022},{"age":99,"percentage":0.0192068},{"age":100,"percentage":0.0179915},{"age":101,"percentage":0.0180857},{"age":102,"percentage":0.0179699},{"age":103,"percentage":0.0178527},{"age":104,"percentage":0.0167734},{"age":105,"percentage":0.0169846},{"age":106,"percentage":0.0139844},{"age":107,"percentage":0.0153586},{"age":108,"percentage":0.0127389},{"age":109,"percentage":0.0137652},{"age":110,"percentage":0.0179949},{"age":111,"percentage":0.0147239},{"age":112,"percentage":0.0121704},{"age":113,"percentage":0.0061920},{"age":114,"percentage":0.0084388},{"age":115,"percentage":0.0115607},{"age":116,"percentage":0.0080645},{"age":117,"percentage":0.0000000},{"age":118,"percentage":0.0161290},{"age":119,"percentage":0.0512821},{"age":120,"percentage":0.0930233}],"Alzheimer's":[{"age":0,"percentage":0.0000000},{"age":1,"percentage":0.0000000},{"age":2,"percentage":0.0000000},{"age":3,"percentage":0.0000000},{"age":4,"percentage":0.0000000},{"age":5,"percentage":0.0000000},{"age":6,"percentage":0.0000000},{"age":7,"percentage":0.0000000},{"age":8,"percentage":0.0000000},{"age":9,"percentage":0.0000000},{"age":10,"percentage":0.0000000},{"age":11,"percentage":0.0000000},{"age":12,"percentage":0.0000000},{"age":13,"percentage":0.0000000},{"age":14,"percentage":0.0000152},{"age":15,"percentage":0.0000000},{"age":16,"percentage":0.0000000},{"age":17,"percentage":0.0000000},{"age":18,"percentage":0.0000000},{"age":19,"percentage":0.0000000},{"age":20,"percentage":0.0000050},{"age":21,"percentage":0.0000000},{"age":22,"percentage":0.0000097},{"age":23,"percentage":0.0000000},{"age":24,"percentage":0.0000000},{"age":25,"percentage":0.0000000},{"age":26,"percentage":0.0000049},{"age":27,"percentage":0.0000049},{"age":28,"percentage":0.0000048},{"age":29,"percentage":0.0000047},{"age":30,"percentage":0.0000091},{"age":31,"percentage":0.0000044},{"age":32,"percentage":0.0000043},{"age":33,"percentage":0.0000123},{"age":34,"percentage":0.0000196},{"age":35,"percentage":0.0000037},{"age":36,"percentage":0.0000036},{"age":37,"percentage":0.0000237},{"age":38,"percentage":0.0000223},{"age":39,"percentage":0.0000450},{"age":40,"percentage":0.0000335},{"age":41,"percentage":0.0000342},{"age":42,"percentage":0.0000413},{"age":43,"percentage":0.0000683},{"age":44,"percentage":0.0000681},{"age":45,"percentage":0.0000989},{"age":46,"percentage":0.0001197},{"age":47,"percentage":0.0001109},{"age":48,"percentage":0.0001483},{"age":49,"percentage":0.0001612},{"age":50,"percentage":0.0001786},{"age":51,"percentage":0.0002447},{"age":52,"percentage":0.0002268},{"age":53,"percentage":0.0002829},{"age":54,"percentage":0.0003032},{"age":55,"percentage":0.0003610},{"age":56,"percentage":0.0004733},{"age":57,"percentage":0.0005605},{"age":58,"percentage":0.0005891},{"age":59,"percentage":0.0007120},{"age":60,"percentage":0.0007560},{"age":61,"percentage":0.0008820},{"age":62,"percentage":0.0010130},{"age":63,"percentage":0.0011446},{"age":64,"percentage":0.0012585},{"age":65,"percentage":0.0013627},{"age":66,"percentage":0.0015569},{"age":67,"percentage":0.0017654},{"age":68,"percentage":0.0020261},{"age":69,"percentage":0.0024088},{"age":70,"percentage":0.0028052},{"age":71,"percentage":0.0033638},{"age":72,"percentage":0.0038041},{"age":73,"percentage":0.0045204},{"age":74,"percentage":0.0054091},{"age":75,"percentage":0.0063263},{"age":76,"percentage":0.0074263},{"age":77,"percentage":0.0085671},{"age":78,"percentage":0.0100219},{"age":79,"percentage":0.0115109},{"age":80,"percentage":0.0128968},{"age":81,"percentage":0.0146317},{"age":82,"percentage":0.0164129},{"age":83,"percentage":0.0180714},{"age":84,"percentage":0.0200734},{"age":85,"percentage":0.0219923},{"age":86,"percentage":0.0239603},{"age":87,"percentage":0.0257799},{"age":88,"percentage":0.0280283},{"age":89,"percentage":0.0296834},{"age":90,"percentage":0.0314801},{"age":91,"percentage":0.0328628},{"age":92,"percentage":0.0345158},{"age":93,"percentage":0.0358687},{"age":94,"percentage":0.0367512},{"age":95,"percentage":0.0378488},{"age":96,"percentage":0.0384969},{"age":97,"percentage":0.0393462},{"age":98,"percentage":0.0395182},{"age":99,"percentage":0.0390239},{"age":100,"percentage":0.0370615},{"age":101,"percentage":0.0362060},{"age":102,"percentage":0.0341660},{"age":103,"percentage":0.0346990},{"age":104,"percentage":0.0306365},{"age":105,"percentage":0.0309207},{"age":106,"percentage":0.0278193},{"age":107,"percentage":0.0257712},{"age":108,"percentage":0.0226224},{"age":109,"percentage":0.0234818},{"age":110,"percentage":0.0134961},{"age":111,"percentage":0.0134969},{"age":112,"percentage":0.0202840},{"age":113,"percentage":0.0216718},{"age":114,"percentage":0.0084388},{"age":115,"percentage":0.0173410},{"age":116,"percentage":0.0000000},{"age":117,"percentage":0.0000000},{"age":118,"percentage":0.0000000},{"age":119,"percentage":0.0000000},{"age":120,"percentage":0.0000000}],"Bronchitis / COPD":[{"age":0,"percentage":0.0011364},{"age":1,"percentage":0.0077460},{"age":2,"percentage":0.0081164},{"age":3,"percentage":0.0079471},{"age":4,"percentage":0.0071960},{"age":5,"percentage":0.0077100},{"age":6,"percentage":0.0078110},{"age":7,"percentage":0.0090603},{"age":8,"percentage":0.0118828},{"age":9,"percentage":0.0140300},{"age":10,"percentage":0.0163514},{"age":11,"percentage":0.0154915},{"age":12,"percentage":0.0147368},{"age":13,"percentage":0.0136366},{"age":14,"percentage":0.0103360},{"age":15,"percentage":0.0082182},{"age":16,"percentage":0.0055181},{"age":17,"percentage":0.0050507},{"age":18,"percentage":0.0041064},{"age":19,"percentage":0.0038882},{"age":20,"percentage":0.0042188},{"age":21,"percentage":0.0039896},{"age":22,"percentage":0.0042980},{"age":23,"percentage":0.0046173},{"age":24,"percentage":0.0044973},{"age":25,"percentage":0.0046723},{"age":26,"percentage":0.0049262},{"age":27,"percentage":0.0049463},{"age":28,"percentage":0.0055632},{"age":29,"percentage":0.0054035},{"age":30,"percentage":0.0053700},{"age":31,"percentage":0.0056077},{"age":32,"percentage":0.0057572},{"age":33,"percentage":0.0058717},{"age":34,"percentage":0.0059657},{"age":35,"percentage":0.0062268},{"age":36,"percentage":0.0065833},{"age":37,"percentage":0.0073160},{"age":38,"percentage":0.0073192},{"age":39,"percentage":0.0079236},{"age":40,"percentage":0.0084668},{"age":41,"percentage":0.0089262},{"age":42,"percentage":0.0096045},{"age":43,"percentage":0.0105385},{"age":44,"percentage":0.0110514},{"age":45,"percentage":0.0119281},{"age":46,"percentage":0.0130397},{"age":47,"percentage":0.0138869},{"age":48,"percentage":0.0153702},{"age":49,"percentage":0.0167669},{"age":50,"percentage":0.0180801},{"age":51,"percentage":0.0196895},{"age":52,"percentage":0.0210828},{"age":53,"percentage":0.0227291},{"age":54,"percentage":0.0242129},{"age":55,"percentage":0.0261159},{"age":56,"percentage":0.0283691},{"age":57,"percentage":0.0303050},{"age":58,"percentage":0.0319988},{"age":59,"percentage":0.0343633},{"age":60,"percentage":0.0363386},{"age":61,"percentage":0.0383977},{"age":62,"percentage":0.0403148},{"age":63,"percentage":0.0425605},{"age":64,"percentage":0.0445049},{"age":65,"percentage":0.0466960},{"age":66,"percentage":0.0487032},{"age":67,"percentage":0.0504790},{"age":68,"percentage":0.0523940},{"age":69,"percentage":0.0540186},{"age":70,"percentage":0.0554935},{"age":71,"percentage":0.0565686},{"age":72,"percentage":0.0565124},{"age":73,"percentage":0.0574241},{"age":74,"percentage":0.0574756},{"age":75,"percentage":0.0569363},{"age":76,"percentage":0.0569768},{"age":77,"percentage":0.0569364},{"age":78,"percentage":0.0554908},{"age":79,"percentage":0.0545504},{"age":80,"percentage":0.0526698},{"age":81,"percentage":0.0512842},{"age":82,"percentage":0.0499013},{"age":83,"percentage":0.0475915},{"age":84,"percentage":0.0458015},{"age":85,"percentage":0.0440289},{"age":86,"percentage":0.0422183},{"age":87,"percentage":0.0400192},{"age":88,"percentage":0.0380208},{"age":89,"percentage":0.0362394},{"age":90,"percentage":0.0334403},{"age":91,"percentage":0.0317133},{"age":92,"percentage":0.0301259},{"age":93,"percentage":0.0283687},{"age":94,"percentage":0.0267327},{"age":95,"percentage":0.0258643},{"age":96,"percentage":0.0241463},{"age":97,"percentage":0.0229225},{"age":98,"percentage":0.0221093},{"age":99,"percentage":0.0202823},{"age":100,"percentage":0.0185996},{"age":101,"percentage":0.0182035},{"age":102,"percentage":0.0159322},{"age":103,"percentage":0.0157408},{"age":104,"percentage":0.0151066},{"age":105,"percentage":0.0144587},{"age":106,"percentage":0.0129375},{"age":107,"percentage":0.0149681},{"age":108,"percentage":0.0133978},{"age":109,"percentage":0.0133603},{"age":110,"percentage":0.0141388},{"age":111,"percentage":0.0073620},{"age":112,"percentage":0.0141988},{"age":113,"percentage":0.0154799},{"age":114,"percentage":0.0084388},{"age":115,"percentage":0.0115607},{"age":116,"percentage":0.0161290},{"age":117,"percentage":0.0000000},{"age":118,"percentage":0.0000000},{"age":119,"percentage":0.0000000},{"age":120,"percentage":0.0000000}],"Cancer":[{"age":0,"percentage":0.0014911},{"age":1,"percentage":0.0294714},{"age":2,"percentage":0.0763752},{"age":3,"percentage":0.1088070},{"age":4,"percentage":0.1320335},{"age":5,"percentage":0.1511830},{"age":6,"percentage":0.1577877},{"age":7,"percentage":0.1599739},{"age":8,"percentage":0.1557697},{"age":9,"percentage":0.1573630},{"age":10,"percentage":0.1520487},{"age":11,"percentage":0.1434468},{"age":12,"percentage":0.1336608},{"age":13,"percentage":0.1171157},{"age":14,"percentage":0.1030399},{"age":15,"percentage":0.0846598},{"age":16,"percentage":0.0633774},{"age":17,"percentage":0.0551090},{"age":18,"percentage":0.0477264},{"age":19,"percentage":0.0470316},{"age":20,"percentage":0.0498136},{"age":21,"percentage":0.0490979},{"age":22,"percentage":0.0518181},{"age":23,"percentage":0.0560713},{"age":24,"percentage":0.0603945},{"age":25,"percentage":0.0642805},{"age":26,"percentage":0.0698098},{"age":27,"percentage":0.0760070},{"age":28,"percentage":0.0799753},{"age":29,"percentage":0.0874144},{"age":30,"percentage":0.0930707},{"age":31,"percentage":0.1030233},{"age":32,"percentage":0.1097962},{"age":33,"percentage":0.1185416},{"age":34,"percentage":0.1269605},{"age":35,"percentage":0.1356917},{"age":36,"percentage":0.1458071},{"age":37,"percentage":0.1556813},{"age":38,"percentage":0.1650799},{"age":39,"percentage":0.1743732},{"age":40,"percentage":0.1842676},{"age":41,"percentage":0.1967199},{"age":42,"percentage":0.2061398},{"age":43,"percentage":0.2198537},{"age":44,"percentage":0.2298593},{"age":45,"percentage":0.2402602},{"age":46,"percentage":0.2517186},{"age":47,"percentage":0.2616918},{"age":48,"percentage":0.2724505},{"age":49,"percentage":0.2832755},{"age":50,"percentage":0.2905391},{"age":51,"percentage":0.3011902},{"age":52,"percentage":0.3083023},{"age":53,"percentage":0.3152808},{"age":54,"percentage":0.3211159},{"age":55,"percentage":0.3265934},{"age":56,"percentage":0.3306183},{"age":57,"percentage":0.3341940},{"age":58,"percentage":0.3374419},{"age":59,"percentage":0.3396729},{"age":60,"percentage":0.3395709},{"age":61,"percentage":0.3406990},{"age":62,"percentage":0.3374327},{"age":63,"percentage":0.3364574},{"age":64,"percentage":0.3351214},{"age":65,"percentage":0.3307709},{"age":66,"percentage":0.3302032},{"age":67,"percentage":0.3246151},{"age":68,"percentage":0.3197880},{"age":69,"percentage":0.3141862},{"age":70,"percentage":0.3062160},{"age":71,"percentage":0.3002181},{"age":72,"percentage":0.2908405},{"age":73,"percentage":0.2817727},{"age":74,"percentage":0.2725726},{"age":75,"percentage":0.2626818},{"age":76,"percentage":0.2534642},{"age":77,"percentage":0.2433355},{"age":78,"percentage":0.2319347},{"age":79,"percentage":0.2217406},{"age":80,"percentage":0.2103593},{"age":81,"percentage":0.2003584},{"age":82,"percentage":0.1888541},{"age":83,"percentage":0.1781128},{"age":84,"percentage":0.1674913},{"age":85,"percentage":0.1566989},{"age":86,"percentage":0.1466709},{"age":87,"percentage":0.1373489},{"age":88,"percentage":0.1276809},{"age":89,"percentage":0.1181245},{"age":90,"percentage":0.1079110},{"age":91,"percentage":0.0993389},{"age":92,"percentage":0.0921790},{"age":93,"percentage":0.0849269},{"age":94,"percentage":0.0783743},{"age":95,"percentage":0.0721343},{"age":96,"percentage":0.0660034},{"age":97,"percentage":0.0609740},{"age":98,"percentage":0.0561372},{"age":99,"percentage":0.0511609},{"age":100,"percentage":0.0448387},{"age":101,"percentage":0.0402820},{"age":102,"percentage":0.0382414},{"age":103,"percentage":0.0366624},{"age":104,"percentage":0.0344463},{"age":105,"percentage":0.0310513},{"age":106,"percentage":0.0327550},{"age":107,"percentage":0.0308473},{"age":108,"percentage":0.0325060},{"age":109,"percentage":0.0319838},{"age":110,"percentage":0.0327763},{"age":111,"percentage":0.0319018},{"age":112,"percentage":0.0223124},{"age":113,"percentage":0.0278638},{"age":114,"percentage":0.0253165},{"age":115,"percentage":0.0751445},{"age":116,"percentage":0.0645161},{"age":117,"percentage":0.0416667},{"age":118,"percentage":0.0161290},{"age":119,"percentage":0.1282051},{"age":120,"percentage":0.0697674}],"Circulatory Diseases":[{"age":0,"percentage":0.0005056},{"age":1,"percentage":0.0009821},{"age":2,"percentage":0.0009577},{"age":3,"percentage":0.0010244},{"age":4,"percentage":0.0009984},{"age":5,"percentage":0.0011045},{"age":6,"percentage":0.0012629},{"age":7,"percentage":0.0017318},{"age":8,"percentage":0.0016900},{"age":9,"percentage":0.0017876},{"age":10,"percentage":0.0017744},{"age":11,"percentage":0.0021160},{"age":12,"percentage":0.0024094},{"age":13,"percentage":0.0028944},{"age":14,"percentage":0.0029836},{"age":15,"percentage":0.0023398},{"age":16,"percentage":0.0018908},{"age":17,"percentage":0.0018330},{"age":18,"percentage":0.0016845},{"age":19,"percentage":0.0018330},{"age":20,"percentage":0.0019992},{"age":21,"percentage":0.0021835},{"age":22,"percentage":0.0022412},{"age":23,"percentage":0.0024020},{"age":24,"percentage":0.0026766},{"age":25,"percentage":0.0030523},{"age":26,"percentage":0.0030080},{"age":27,"percentage":0.0034692},{"age":28,"percentage":0.0035065},{"age":29,"percentage":0.0038830},{"age":30,"percentage":0.0040921},{"age":31,"percentage":0.0038857},{"age":32,"percentage":0.0044542},{"age":33,"percentage":0.0045258},{"age":34,"percentage":0.0049610},{"age":35,"percentage":0.0048539},{"age":36,"percentage":0.0053857},{"age":37,"percentage":0.0055996},{"age":38,"percentage":0.0059887},{"age":39,"percentage":0.0059877},{"age":40,"percentage":0.0061430},{"age":41,"percentage":0.0061305},{"age":42,"percentage":0.0064896},{"age":43,"percentage":0.0066840},{"age":44,"percentage":0.0067459},{"age":45,"percentage":0.0070184},{"age":46,"percentage":0.0070587},{"age":47,"percentage":0.0074347},{"age":48,"percentage":0.0077928},{"age":49,"percentage":0.0075747},{"age":50,"percentage":0.0077292},{"age":51,"percentage":0.0081334},{"age":52,"percentage":0.0084324},{"age":53,"percentage":0.0087960},{"age":54,"percentage":0.0091970},{"age":55,"percentage":0.0094045},{"age":56,"percentage":0.0097773},{"age":57,"percentage":0.0107226},{"age":58,"percentage":0.0111920},{"age":59,"percentage":0.0118199},{"age":60,"percentage":0.0125111},{"age":61,"percentage":0.0130995},{"age":62,"percentage":0.0138965},{"age":63,"percentage":0.0144331},{"age":64,"percentage":0.0152887},{"age":65,"percentage":0.0159434},{"age":66,"percentage":0.0168289},{"age":67,"percentage":0.0172420},{"age":68,"percentage":0.0180082},{"age":69,"percentage":0.0185921},{"age":70,"percentage":0.0192681},{"age":71,"percentage":0.0196738},{"age":72,"percentage":0.0202883},{"age":73,"percentage":0.0207057},{"age":74,"percentage":0.0212608},{"age":75,"percentage":0.0216615},{"age":76,"percentage":0.0222415},{"age":77,"percentage":0.0225897},{"age":78,"percentage":0.0230037},{"age":79,"percentage":0.0233907},{"age":80,"percentage":0.0239222},{"age":81,"percentage":0.0244763},{"age":82,"percentage":0.0247228},{"age":83,"percentage":0.0253208},{"age":84,"percentage":0.0258088},{"age":85,"percentage":0.0262934},{"age":86,"percentage":0.0269430},{"age":87,"percentage":0.0274712},{"age":88,"percentage":0.0277464},{"age":89,"percentage":0.0282623},{"age":90,"percentage":0.0294290},{"age":91,"percentage":0.0298443},{"age":92,"percentage":0.0304550},{"age":93,"percentage":0.0313503},{"age":94,"percentage":0.0317299},{"age":95,"percentage":0.0327000},{"age":96,"percentage":0.0333313},{"age":97,"percentage":0.0343503},{"age":98,"percentage":0.0345310},{"age":99,"percentage":0.0353558},{"age":100,"percentage":0.0376459},{"age":101,"percentage":0.0386114},{"age":102,"percentage":0.0391389},{"age":103,"percentage":0.0414804},{"age":104,"percentage":0.0424890},{"age":105,"percentage":0.0432454},{"age":106,"percentage":0.0456925},{"age":107,"percentage":0.0438631},{"age":108,"percentage":0.0498572},{"age":109,"percentage":0.0578947},{"age":110,"percentage":0.0449871},{"age":111,"percentage":0.0441718},{"age":112,"percentage":0.0507099},{"age":113,"percentage":0.0557276},{"age":114,"percentage":0.0379747},{"age":115,"percentage":0.0578035},{"age":116,"percentage":0.0483871},{"age":117,"percentage":0.0138889},{"age":118,"percentage":0.0967742},{"age":119,"percentage":0.0256410},{"age":120,"percentage":0.0465116}],"Congenital Anomalies":[{"age":0,"percentage":0.1916108},{"age":1,"percentage":0.1719812},{"age":2,"percentage":0.1123960},{"age":3,"percentage":0.0939062},{"age":4,"percentage":0.0851276},{"age":5,"percentage":0.0782465},{"age":6,"percentage":0.0688494},{"age":7,"percentage":0.0634976},{"age":8,"percentage":0.0608397},{"age":9,"percentage":0.0586116},{"age":10,"percentage":0.0565337},{"age":11,"percentage":0.0531623},{"age":12,"percentage":0.0502222},{"age":13,"percentage":0.0458051},{"age":14,"percentage":0.0367315},{"age":15,"percentage":0.0275476},{"age":16,"percentage":0.0206119},{"age":17,"percentage":0.0167015},{"age":18,"percentage":0.0135516},{"age":19,"percentage":0.0122401},{"age":20,"percentage":0.0124309},{"age":21,"percentage":0.0115721},{"age":22,"percentage":0.0110408},{"age":23,"percentage":0.0112437},{"age":24,"percentage":0.0108945},{"age":25,"percentage":0.0106434},{"age":26,"percentage":0.0107202},{"age":27,"percentage":0.0104611},{"age":28,"percentage":0.0100186},{"age":29,"percentage":0.0095812},{"age":30,"percentage":0.0086871},{"age":31,"percentage":0.0088752},{"age":32,"percentage":0.0080908},{"age":33,"percentage":0.0083500},{"age":34,"percentage":0.0076573},{"age":35,"percentage":0.0075140},{"age":36,"percentage":0.0069562},{"age":37,"percentage":0.0064900},{"age":38,"percentage":0.0063843},{"age":39,"percentage":0.0059217},{"age":40,"percentage":0.0055237},{"age":41,"percentage":0.0052153},{"age":42,"percentage":0.0050051},{"age":43,"percentage":0.0048159},{"age":44,"percentage":0.0046165},{"age":45,"percentage":0.0045240},{"age":46,"percentage":0.0041243},{"age":47,"percentage":0.0039416},{"age":48,"percentage":0.0037369},{"age":49,"percentage":0.0036033},{"age":50,"percentage":0.0032291},{"age":51,"percentage":0.0030550},{"age":52,"percentage":0.0030284},{"age":53,"percentage":0.0029305},{"age":54,"percentage":0.0027781},{"age":55,"percentage":0.0026525},{"age":56,"percentage":0.0025712},{"age":57,"percentage":0.0023723},{"age":58,"percentage":0.0022362},{"age":59,"percentage":0.0020937},{"age":60,"percentage":0.0019192},{"age":61,"percentage":0.0018449},{"age":62,"percentage":0.0016657},{"age":63,"percentage":0.0015638},{"age":64,"percentage":0.0014151},{"age":65,"percentage":0.0013300},{"age":66,"percentage":0.0012451},{"age":67,"percentage":0.0011422},{"age":68,"percentage":0.0010549},{"age":69,"percentage":0.0010354},{"age":70,"percentage":0.0009222},{"age":71,"percentage":0.0008529},{"age":72,"percentage":0.0008428},{"age":73,"percentage":0.0008777},{"age":74,"percentage":0.0007934},{"age":75,"percentage":0.0007803},{"age":76,"percentage":0.0007363},{"age":77,"percentage":0.0007403},{"age":78,"percentage":0.0007327},{"age":79,"percentage":0.0006879},{"age":80,"percentage":0.0006985},{"age":81,"percentage":0.0006126},{"age":82,"percentage":0.0006336},{"age":83,"percentage":0.0005961},{"age":84,"percentage":0.0006149},{"age":85,"percentage":0.0005512},{"age":86,"percentage":0.0005270},{"age":87,"percentage":0.0005227},{"age":88,"percentage":0.0005105},{"age":89,"percentage":0.0004958},{"age":90,"percentage":0.0004671},{"age":91,"percentage":0.0004304},{"age":92,"percentage":0.0004045},{"age":93,"percentage":0.0003941},{"age":94,"percentage":0.0003626},{"age":95,"percentage":0.0004090},{"age":96,"percentage":0.0003727},{"age":97,"percentage":0.0004183},{"age":98,"percentage":0.0003548},{"age":99,"percentage":0.0003877},{"age":100,"percentage":0.0003991},{"age":101,"percentage":0.0004644},{"age":102,"percentage":0.0003167},{"age":103,"percentage":0.0004125},{"age":104,"percentage":0.0002646},{"age":105,"percentage":0.0003920},{"age":106,"percentage":0.0002991},{"age":107,"percentage":0.0005206},{"age":108,"percentage":0.0006589},{"age":109,"percentage":0.0008097},{"age":110,"percentage":0.0000000},{"age":111,"percentage":0.0000000},{"age":112,"percentage":0.0000000},{"age":113,"percentage":0.0000000},{"age":114,"percentage":0.0000000},{"age":115,"percentage":0.0000000},{"age":116,"percentage":0.0000000},{"age":117,"percentage":0.0000000},{"age":118,"percentage":0.0000000},{"age":119,"percentage":0.0000000},{"age":120,"percentage":0.0000000}],"Diabetes":[{"age":0,"percentage":0.0000953},{"age":1,"percentage":0.0009346},{"age":2,"percentage":0.0012689},{"age":3,"percentage":0.0011176},{"age":4,"percentage":0.0014128},{"age":5,"percentage":0.0014655},{"age":6,"percentage":0.0021515},{"age":7,"percentage":0.0026353},{"age":8,"percentage":0.0038553},{"age":9,"percentage":0.0047398},{"age":10,"percentage":0.0046133},{"age":11,"percentage":0.0064526},{"age":12,"percentage":0.0057310},{"age":13,"percentage":0.0053808},{"age":14,"percentage":0.0044145},{"age":15,"percentage":0.0032965},{"age":16,"percentage":0.0028483},{"age":17,"percentage":0.0024001},{"age":18,"percentage":0.0028255},{"age":19,"percentage":0.0032418},{"age":20,"percentage":0.0038079},{"age":21,"percentage":0.0043909},{"age":22,"percentage":0.0049868},{"age":23,"percentage":0.0057913},{"age":24,"percentage":0.0070255},{"age":25,"percentage":0.0074924},{"age":26,"percentage":0.0089253},{"age":27,"percentage":0.0104125},{"age":28,"percentage":0.0114732},{"age":29,"percentage":0.0125473},{"age":30,"percentage":0.0131689},{"age":31,"percentage":0.0142004},{"age":32,"percentage":0.0156834},{"age":33,"percentage":0.0158630},{"age":34,"percentage":0.0165314},{"age":35,"percentage":0.0174157},{"age":36,"percentage":0.0176809},{"age":37,"percentage":0.0183595},{"age":38,"percentage":0.0194433},{"age":39,"percentage":0.0195359},{"age":40,"percentage":0.0198155},{"age":41,"percentage":0.0204113},{"age":42,"percentage":0.0207469},{"age":43,"percentage":0.0210429},{"age":44,"percentage":0.0214641},{"age":45,"percentage":0.0224437},{"age":46,"percentage":0.0222185},{"age":47,"percentage":0.0229777},{"age":48,"percentage":0.0236239},{"age":49,"percentage":0.0243475},{"age":50,"percentage":0.0246881},{"age":51,"percentage":0.0249957},{"age":52,"percentage":0.0258221},{"age":53,"percentage":0.0264254},{"age":54,"percentage":0.0269376},{"age":55,"percentage":0.0272753},{"age":56,"percentage":0.0279885},{"age":57,"percentage":0.0285789},{"age":58,"percentage":0.0288334},{"age":59,"percentage":0.0290916},{"age":60,"percentage":0.0290969},{"age":61,"percentage":0.0297777},{"age":62,"percentage":0.0296609},{"age":63,"percentage":0.0298348},{"age":64,"percentage":0.0299836},{"age":65,"percentage":0.0301933},{"age":66,"percentage":0.0302250},{"age":67,"percentage":0.0303294},{"age":68,"percentage":0.0302622},{"age":69,"percentage":0.0301359},{"age":70,"percentage":0.0298792},{"age":71,"percentage":0.0297838},{"age":72,"percentage":0.0295372},{"age":73,"percentage":0.0294923},{"age":74,"percentage":0.0293338},{"age":75,"percentage":0.0290172},{"age":76,"percentage":0.0284636},{"age":77,"percentage":0.0278174},{"age":78,"percentage":0.0275346},{"age":79,"percentage":0.0269882},{"age":80,"percentage":0.0265293},{"age":81,"percentage":0.0257214},{"age":82,"percentage":0.0250077},{"age":83,"percentage":0.0242491},{"age":84,"percentage":0.0235187},{"age":85,"percentage":0.0228798},{"age":86,"percentage":0.0217230},{"age":87,"percentage":0.0209278},{"age":88,"percentage":0.0201998},{"age":89,"percentage":0.0192608},{"age":90,"percentage":0.0181809},{"age":91,"percentage":0.0172199},{"age":92,"percentage":0.0163010},{"age":93,"percentage":0.0156785},{"age":94,"percentage":0.0145196},{"age":95,"percentage":0.0138346},{"age":96,"percentage":0.0133868},{"age":97,"percentage":0.0124780},{"age":98,"percentage":0.0116343},{"age":99,"percentage":0.0113852},{"age":100,"percentage":0.0104567},{"age":101,"percentage":0.0098504},{"age":102,"percentage":0.0096184},{"age":103,"percentage":0.0081509},{"age":104,"percentage":0.0088100},{"age":105,"percentage":0.0088407},{"age":106,"percentage":0.0074783},{"age":107,"percentage":0.0084602},{"age":108,"percentage":0.0068087},{"age":109,"percentage":0.0068826},{"age":110,"percentage":0.0077121},{"age":111,"percentage":0.0036810},{"age":112,"percentage":0.0040568},{"age":113,"percentage":0.0030960},{"age":114,"percentage":0.0126582},{"age":115,"percentage":0.0057803},{"age":116,"percentage":0.0000000},{"age":117,"percentage":0.0000000},{"age":118,"percentage":0.0161290},{"age":119,"percentage":0.0000000},{"age":120,"percentage":0.0000000}],"Digestive Tract Diseases":[{"age":0,"percentage":0.0003301},{"age":1,"percentage":0.0005346},{"age":2,"percentage":0.0005626},{"age":3,"percentage":0.0004501},{"age":4,"percentage":0.0006405},{"age":5,"percentage":0.0005310},{"age":6,"percentage":0.0004911},{"age":7,"percentage":0.0004518},{"age":8,"percentage":0.0003169},{"age":9,"percentage":0.0004063},{"age":10,"percentage":0.0003822},{"age":11,"percentage":0.0003657},{"age":12,"percentage":0.0008421},{"age":13,"percentage":0.0005828},{"age":14,"percentage":0.0005784},{"age":15,"percentage":0.0003804},{"age":16,"percentage":0.0003327},{"age":17,"percentage":0.0003626},{"age":18,"percentage":0.0003229},{"age":19,"percentage":0.0003888},{"age":20,"percentage":0.0003858},{"age":21,"percentage":0.0004157},{"age":22,"percentage":0.0005385},{"age":23,"percentage":0.0005845},{"age":24,"percentage":0.0005591},{"age":25,"percentage":0.0006816},{"age":26,"percentage":0.0007594},{"age":27,"percentage":0.0008552},{"age":28,"percentage":0.0009874},{"age":29,"percentage":0.0010012},{"age":30,"percentage":0.0010876},{"age":31,"percentage":0.0009891},{"age":32,"percentage":0.0013158},{"age":33,"percentage":0.0013089},{"age":34,"percentage":0.0013972},{"age":35,"percentage":0.0015185},{"age":36,"percentage":0.0016207},{"age":37,"percentage":0.0016487},{"age":38,"percentage":0.0018378},{"age":39,"percentage":0.0019479},{"age":40,"percentage":0.0018803},{"age":41,"percentage":0.0020067},{"age":42,"percentage":0.0023082},{"age":43,"percentage":0.0021460},{"age":44,"percentage":0.0023530},{"age":45,"percentage":0.0023757},{"age":46,"percentage":0.0024831},{"age":47,"percentage":0.0025055},{"age":48,"percentage":0.0024705},{"age":49,"percentage":0.0024973},{"age":50,"percentage":0.0024307},{"age":51,"percentage":0.0024984},{"age":52,"percentage":0.0025108},{"age":53,"percentage":0.0026169},{"age":54,"percentage":0.0026329},{"age":55,"percentage":0.0025801},{"age":56,"percentage":0.0026545},{"age":57,"percentage":0.0026775},{"age":58,"percentage":0.0026823},{"age":59,"percentage":0.0027068},{"age":60,"percentage":0.0027014},{"age":61,"percentage":0.0025700},{"age":62,"percentage":0.0026947},{"age":63,"percentage":0.0026932},{"age":64,"percentage":0.0026742},{"age":65,"percentage":0.0027018},{"age":66,"percentage":0.0026800},{"age":67,"percentage":0.0027090},{"age":68,"percentage":0.0026610},{"age":69,"percentage":0.0026927},{"age":70,"percentage":0.0026362},{"age":71,"percentage":0.0027339},{"age":72,"percentage":0.0026665},{"age":73,"percentage":0.0027018},{"age":74,"percentage":0.0027658},{"age":75,"percentage":0.0027509},{"age":76,"percentage":0.0027332},{"age":77,"percentage":0.0027411},{"age":78,"percentage":0.0027764},{"age":79,"percentage":0.0027929},{"age":80,"percentage":0.0027703},{"age":81,"percentage":0.0028365},{"age":82,"percentage":0.0027322},{"age":83,"percentage":0.0027457},{"age":84,"percentage":0.0027681},{"age":85,"percentage":0.0026690},{"age":86,"percentage":0.0028076},{"age":87,"percentage":0.0027085},{"age":88,"percentage":0.0026366},{"age":89,"percentage":0.0026634},{"age":90,"percentage":0.0024833},{"age":91,"percentage":0.0025105},{"age":92,"percentage":0.0024090},{"age":93,"percentage":0.0024114},{"age":94,"percentage":0.0023119},{"age":95,"percentage":0.0022624},{"age":96,"percentage":0.0020459},{"age":97,"percentage":0.0020389},{"age":98,"percentage":0.0019856},{"age":99,"percentage":0.0017228},{"age":100,"percentage":0.0017578},{"age":101,"percentage":0.0016637},{"age":102,"percentage":0.0017315},{"age":103,"percentage":0.0013530},{"age":104,"percentage":0.0012964},{"age":105,"percentage":0.0016549},{"age":106,"percentage":0.0012713},{"age":107,"percentage":0.0011714},{"age":108,"percentage":0.0008785},{"age":109,"percentage":0.0004049},{"age":110,"percentage":0.0032134},{"age":111,"percentage":0.0024540},{"age":112,"percentage":0.0020284},{"age":113,"percentage":0.0030960},{"age":114,"percentage":0.0000000},{"age":115,"percentage":0.0000000},{"age":116,"percentage":0.0000000},{"age":117,"percentage":0.0000000},{"age":118,"percentage":0.0000000},{"age":119,"percentage":0.0000000},{"age":120,"percentage":0.0000000}],"Heart Diseases":[{"age":0,"percentage":0.0136784},{"age":1,"percentage":0.0434982},{"age":2,"percentage":0.0319148},{"age":3,"percentage":0.0272871},{"age":4,"percentage":0.0275784},{"age":5,"percentage":0.0272291},{"age":6,"percentage":0.0286717},{"age":7,"percentage":0.0285112},{"age":8,"percentage":0.0312384},{"age":9,"percentage":0.0277349},{"age":10,"percentage":0.0307373},{"age":11,"percentage":0.0340918},{"age":12,"percentage":0.0353684},{"age":13,"percentage":0.0360730},{"age":14,"percentage":0.0341284},{"age":15,"percentage":0.0311092},{"age":16,"percentage":0.0253834},{"age":17,"percentage":0.0229390},{"age":18,"percentage":0.0215382},{"age":19,"percentage":0.0232027},{"age":20,"percentage":0.0245310},{"age":21,"percentage":0.0271243},{"age":22,"percentage":0.0280387},{"age":23,"percentage":0.0311180},{"age":24,"percentage":0.0344892},{"age":25,"percentage":0.0388745},{"age":26,"percentage":0.0416334},{"age":27,"percentage":0.0465964},{"age":28,"percentage":0.0515331},{"age":29,"percentage":0.0554334},{"age":30,"percentage":0.0621423},{"age":31,"percentage":0.0689089},{"age":32,"percentage":0.0758490},{"age":33,"percentage":0.0822980},{"age":34,"percentage":0.0910679},{"age":35,"percentage":0.1008678},{"age":36,"percentage":0.1097247},{"age":37,"percentage":0.1202117},{"age":38,"percentage":0.1309025},{"age":39,"percentage":0.1412171},{"age":40,"percentage":0.1540631},{"age":41,"percentage":0.1646184},{"age":42,"percentage":0.1758492},{"age":43,"percentage":0.1857299},{"age":44,"percentage":0.1953188},{"age":45,"percentage":0.2058370},{"age":46,"percentage":0.2143531},{"age":47,"percentage":0.2231285},{"age":48,"percentage":0.2288900},{"age":49,"percentage":0.2367554},{"age":50,"percentage":0.2461935},{"age":51,"percentage":0.2512155},{"age":52,"percentage":0.2569864},{"age":53,"percentage":0.2633505},{"age":54,"percentage":0.2690557},{"age":55,"percentage":0.2739624},{"age":56,"percentage":0.2786978},{"age":57,"percentage":0.2834863},{"age":58,"percentage":0.2879776},{"age":59,"percentage":0.2912740},{"age":60,"percentage":0.2965770},{"age":61,"percentage":0.2995937},{"age":62,"percentage":0.3048096},{"age":63,"percentage":0.3065161},{"age":64,"percentage":0.3095725},{"age":65,"percentage":0.3127073},{"age":66,"percentage":0.3133977},{"age":67,"percentage":0.3163414},{"age":68,"percentage":0.3185366},{"age":69,"percentage":0.3203417},{"age":70,"percentage":0.3238741},{"age":71,"percentage":0.3248512},{"age":72,"percentage":0.3286509},{"age":73,"percentage":0.3308137},{"age":74,"percentage":0.3326757},{"age":75,"percentage":0.3361243},{"age":76,"percentage":0.3367839},{"age":77,"percentage":0.3391295},{"age":78,"percentage":0.3418425},{"age":79,"percentage":0.3441209},{"age":80,"percentage":0.3479969},{"age":81,"percentage":0.3501406},{"age":82,"percentage":0.3534900},{"age":83,"percentage":0.3564946},{"age":84,"percentage":0.3593849},{"age":85,"percentage":0.3625353},{"age":86,"percentage":0.3660272},{"age":87,"percentage":0.3690425},{"age":88,"percentage":0.3721063},{"age":89,"percentage":0.3756377},{"age":90,"percentage":0.3820850},{"age":91,"percentage":0.3855702},{"age":92,"percentage":0.3885844},{"age":93,"percentage":0.3916684},{"age":94,"percentage":0.3959768},{"age":95,"percentage":0.3984199},{"age":96,"percentage":0.4033196},{"age":97,"percentage":0.4034915},{"age":98,"percentage":0.4058709},{"age":99,"percentage":0.4090920},{"age":100,"percentage":0.4179763},{"age":101,"percentage":0.4194152},{"age":102,"percentage":0.4222501},{"age":103,"percentage":0.4196710},{"age":104,"percentage":0.4255252},{"age":105,"percentage":0.4263130},{"age":106,"percentage":0.4321717},{"age":107,"percentage":0.4271769},{"age":108,"percentage":0.4199429},{"age":109,"percentage":0.4068826},{"age":110,"percentage":0.4338046},{"age":111,"percentage":0.4098160},{"age":112,"percentage":0.3975659},{"age":113,"percentage":0.3993808},{"age":114,"percentage":0.4683544},{"age":115,"percentage":0.3583815},{"age":116,"percentage":0.4193548},{"age":117,"percentage":0.4166667},{"age":118,"percentage":0.4032258},{"age":119,"percentage":0.4102564},{"age":120,"percentage":0.4651163}],"Homicide":[{"age":0,"percentage":0.0050166},{"age":1,"percentage":0.0420845},{"age":2,"percentage":0.0576645},{"age":3,"percentage":0.0495297},{"age":4,"percentage":0.0421965},{"age":5,"percentage":0.0343231},{"age":6,"percentage":0.0328344},{"age":7,"percentage":0.0312971},{"age":8,"percentage":0.0341695},{"age":9,"percentage":0.0327456},{"age":10,"percentage":0.0330576},{"age":11,"percentage":0.0369393},{"age":12,"percentage":0.0421754},{"age":13,"percentage":0.0529342},{"age":14,"percentage":0.0724126},{"age":15,"percentage":0.0967738},{"age":16,"percentage":0.1092429},{"age":17,"percentage":0.1297548},{"age":18,"percentage":0.1429048},{"age":19,"percentage":0.1526533},{"age":20,"percentage":0.1578283},{"age":21,"percentage":0.1562954},{"age":22,"percentage":0.1594953},{"age":23,"percentage":0.1587042},{"age":24,"percentage":0.1556444},{"age":25,"percentage":0.1523816},{"age":26,"percentage":0.1465181},{"age":27,"percentage":0.1378164},{"age":28,"percentage":0.1295818},{"age":29,"percentage":0.1231988},{"age":30,"percentage":0.1160687},{"age":31,"percentage":0.1033324},{"age":32,"percentage":0.0970937},{"age":33,"percentage":0.0889616},{"age":34,"percentage":0.0822370},{"age":35,"percentage":0.0747256},{"age":36,"percentage":0.0673673},{"age":37,"percentage":0.0604613},{"age":38,"percentage":0.0551553},{"age":39,"percentage":0.0498046},{"age":40,"percentage":0.0444907},{"age":41,"percentage":0.0393997},{"age":42,"percentage":0.0353516},{"age":43,"percentage":0.0313013},{"age":44,"percentage":0.0274540},{"age":45,"percentage":0.0245781},{"age":46,"percentage":0.0221191},{"age":47,"percentage":0.0192100},{"age":48,"percentage":0.0168679},{"age":49,"percentage":0.0148670},{"age":50,"percentage":0.0132750},{"age":51,"percentage":0.0112428},{"age":52,"percentage":0.0101179},{"age":53,"percentage":0.0090266},{"age":54,"percentage":0.0080172},{"age":55,"percentage":0.0070385},{"age":56,"percentage":0.0061534},{"age":57,"percentage":0.0056005},{"age":58,"percentage":0.0047367},{"age":59,"percentage":0.0043157},{"age":60,"percentage":0.0038519},{"age":61,"percentage":0.0034477},{"age":62,"percentage":0.0030797},{"age":63,"percentage":0.0027104},{"age":64,"percentage":0.0023755},{"age":65,"percentage":0.0022321},{"age":66,"percentage":0.0019188},{"age":67,"percentage":0.0017622},{"age":68,"percentage":0.0015494},{"age":69,"percentage":0.0014209},{"age":70,"percentage":0.0013069},{"age":71,"percentage":0.0011290},{"age":72,"percentage":0.0010487},{"age":73,"percentage":0.0009580},{"age":74,"percentage":0.0008880},{"age":75,"percentage":0.0008155},{"age":76,"percentage":0.0007489},{"age":77,"percentage":0.0006370},{"age":78,"percentage":0.0006352},{"age":79,"percentage":0.0005779},{"age":80,"percentage":0.0005468},{"age":81,"percentage":0.0004743},{"age":82,"percentage":0.0004269},{"age":83,"percentage":0.0004106},{"age":84,"percentage":0.0003565},{"age":85,"percentage":0.0003309},{"age":86,"percentage":0.0003000},{"age":87,"percentage":0.0002673},{"age":88,"percentage":0.0002574},{"age":89,"percentage":0.0002002},{"age":90,"percentage":0.0001896},{"age":91,"percentage":0.0001513},{"age":92,"percentage":0.0001482},{"age":93,"percentage":0.0001328},{"age":94,"percentage":0.0001343},{"age":95,"percentage":0.0001257},{"age":96,"percentage":0.0000654},{"age":97,"percentage":0.0000833},{"age":98,"percentage":0.0000705},{"age":99,"percentage":0.0003709},{"age":100,"percentage":0.0000998},{"age":101,"percentage":0.0001178},{"age":102,"percentage":0.0000211},{"age":103,"percentage":0.0001320},{"age":104,"percentage":0.0000265},{"age":105,"percentage":0.0001742},{"age":106,"percentage":0.0001496},{"age":107,"percentage":0.0001302},{"age":108,"percentage":0.0000000},{"age":109,"percentage":0.0012146},{"age":110,"percentage":0.0000000},{"age":111,"percentage":0.0012270},{"age":112,"percentage":0.0000000},{"age":113,"percentage":0.0000000},{"age":114,"percentage":0.0000000},{"age":115,"percentage":0.0057803},{"age":116,"percentage":0.0000000},{"age":117,"percentage":0.0138889},{"age":118,"percentage":0.0161290},{"age":119,"percentage":0.0256410},{"age":120,"percentage":0.0000000}],"Hypertension":[{"age":0,"percentage":0.0000857},{"age":1,"percentage":0.0002970},{"age":2,"percentage":0.0002634},{"age":3,"percentage":0.0002173},{"age":4,"percentage":0.0003579},{"age":5,"percentage":0.0003823},{"age":6,"percentage":0.0005145},{"age":7,"percentage":0.0005020},{"age":8,"percentage":0.0004489},{"age":9,"percentage":0.0004875},{"age":10,"percentage":0.0008189},{"age":11,"percentage":0.0006270},{"age":12,"percentage":0.0004211},{"age":13,"percentage":0.0005439},{"age":14,"percentage":0.0003806},{"age":15,"percentage":0.0005417},{"age":16,"percentage":0.0005112},{"age":17,"percentage":0.0005011},{"age":18,"percentage":0.0005274},{"age":19,"percentage":0.0008079},{"age":20,"percentage":0.0010973},{"age":21,"percentage":0.0014286},{"age":22,"percentage":0.0016299},{"age":23,"percentage":0.0019943},{"age":24,"percentage":0.0024936},{"age":25,"percentage":0.0028992},{"age":26,"percentage":0.0037723},{"age":27,"percentage":0.0041349},{"age":28,"percentage":0.0046095},{"age":29,"percentage":0.0056701},{"age":30,"percentage":0.0061857},{"age":31,"percentage":0.0070560},{"age":32,"percentage":0.0076692},{"age":33,"percentage":0.0087398},{"age":34,"percentage":0.0096198},{"age":35,"percentage":0.0098980},{"age":36,"percentage":0.0107032},{"age":37,"percentage":0.0120388},{"age":38,"percentage":0.0130941},{"age":39,"percentage":0.0139863},{"age":40,"percentage":0.0152598},{"age":41,"percentage":0.0155458},{"age":42,"percentage":0.0163808},{"age":43,"percentage":0.0170517},{"age":44,"percentage":0.0175120},{"age":45,"percentage":0.0181156},{"age":46,"percentage":0.0185547},{"age":47,"percentage":0.0189951},{"age":48,"percentage":0.0192092},{"age":49,"percentage":0.0192036},{"age":50,"percentage":0.0189623},{"age":51,"percentage":0.0193361},{"age":52,"percentage":0.0191994},{"age":53,"percentage":0.0188816},{"age":54,"percentage":0.0188222},{"age":55,"percentage":0.0186149},{"age":56,"percentage":0.0182993},{"age":57,"percentage":0.0179019},{"age":58,"percentage":0.0175202},{"age":59,"percentage":0.0175309},{"age":60,"percentage":0.0172810},{"age":61,"percentage":0.0170157},{"age":62,"percentage":0.0166793},{"age":63,"percentage":0.0165259},{"age":64,"percentage":0.0162630},{"age":65,"percentage":0.0160094},{"age":66,"percentage":0.0156384},{"age":67,"percentage":0.0155915},{"age":68,"percentage":0.0154983},{"age":69,"percentage":0.0155065},{"age":70,"percentage":0.0154917},{"age":71,"percentage":0.0155571},{"age":72,"percentage":0.0156833},{"age":73,"percentage":0.0158215},{"age":74,"percentage":0.0159172},{"age":75,"percentage":0.0163201},{"age":76,"percentage":0.0163904},{"age":77,"percentage":0.0167741},{"age":78,"percentage":0.0169211},{"age":79,"percentage":0.0175060},{"age":80,"percentage":0.0181612},{"age":81,"percentage":0.0184499},{"age":82,"percentage":0.0189641},{"age":83,"percentage":0.0194869},{"age":84,"percentage":0.0200882},{"age":85,"percentage":0.0207888},{"age":86,"percentage":0.0215020},{"age":87,"percentage":0.0220280},{"age":88,"percentage":0.0228508},{"age":89,"percentage":0.0237502},{"age":90,"percentage":0.0244185},{"age":91,"percentage":0.0253500},{"age":92,"percentage":0.0260062},{"age":93,"percentage":0.0268364},{"age":94,"percentage":0.0275431},{"age":95,"percentage":0.0284442},{"age":96,"percentage":0.0292298},{"age":97,"percentage":0.0299410},{"age":98,"percentage":0.0312597},{"age":99,"percentage":0.0317822},{"age":100,"percentage":0.0320826},{"age":101,"percentage":0.0327885},{"age":102,"percentage":0.0332052},{"age":103,"percentage":0.0338080},{"age":104,"percentage":0.0349489},{"age":105,"percentage":0.0334030},{"age":106,"percentage":0.0321567},{"age":107,"percentage":0.0311076},{"age":108,"percentage":0.0292115},{"age":109,"percentage":0.0344130},{"age":110,"percentage":0.0257069},{"age":111,"percentage":0.0306748},{"age":112,"percentage":0.0365112},{"age":113,"percentage":0.0371517},{"age":114,"percentage":0.0253165},{"age":115,"percentage":0.0173410},{"age":116,"percentage":0.0241935},{"age":117,"percentage":0.0416667},{"age":118,"percentage":0.0645161},{"age":119,"percentage":0.0000000},{"age":120,"percentage":0.0000000}],"Influenza and Pneumonia":[{"age":0,"percentage":0.0303395},{"age":1,"percentage":0.0644078},{"age":2,"percentage":0.0409888},{"age":3,"percentage":0.0334958},{"age":4,"percentage":0.0279740},{"age":5,"percentage":0.0268893},{"age":6,"percentage":0.0253508},{"age":7,"percentage":0.0231653},{"age":8,"percentage":0.0238711},{"age":9,"percentage":0.0242139},{"age":10,"percentage":0.0228755},{"age":11,"percentage":0.0239818},{"age":12,"percentage":0.0220819},{"age":13,"percentage":0.0200664},{"age":14,"percentage":0.0163031},{"age":15,"percentage":0.0130246},{"age":16,"percentage":0.0098840},{"age":17,"percentage":0.0093695},{"age":18,"percentage":0.0083796},{"age":19,"percentage":0.0079480},{"age":20,"percentage":0.0087231},{"age":21,"percentage":0.0084904},{"age":22,"percentage":0.0091198},{"age":23,"percentage":0.0094066},{"age":24,"percentage":0.0097268},{"age":25,"percentage":0.0102928},{"age":26,"percentage":0.0111394},{"age":27,"percentage":0.0115495},{"age":28,"percentage":0.0120849},{"age":29,"percentage":0.0123975},{"age":30,"percentage":0.0132867},{"age":31,"percentage":0.0137279},{"age":32,"percentage":0.0141291},{"age":33,"percentage":0.0144351},{"age":34,"percentage":0.0150753},{"age":35,"percentage":0.0149197},{"age":36,"percentage":0.0155582},{"age":37,"percentage":0.0155427},{"age":38,"percentage":0.0156912},{"age":39,"percentage":0.0160363},{"age":40,"percentage":0.0159768},{"age":41,"percentage":0.0156273},{"age":42,"percentage":0.0158414},{"age":43,"percentage":0.0159627},{"age":44,"percentage":0.0153868},{"age":45,"percentage":0.0153146},{"age":46,"percentage":0.0149057},{"age":47,"percentage":0.0150518},{"age":48,"percentage":0.0145839},{"age":49,"percentage":0.0147457},{"age":50,"percentage":0.0147081},{"age":51,"percentage":0.0144014},{"age":52,"percentage":0.0140826},{"age":53,"percentage":0.0140967},{"age":54,"percentage":0.0141809},{"age":55,"percentage":0.0143727},{"age":56,"percentage":0.0142181},{"age":57,"percentage":0.0140855},{"age":58,"percentage":0.0144104},{"age":59,"percentage":0.0144222},{"age":60,"percentage":0.0150730},{"age":61,"percentage":0.0149150},{"age":62,"percentage":0.0152699},{"age":63,"percentage":0.0157098},{"age":64,"percentage":0.0157677},{"age":65,"percentage":0.0162902},{"age":66,"percentage":0.0164525},{"age":67,"percentage":0.0171006},{"age":68,"percentage":0.0178408},{"age":69,"percentage":0.0183316},{"age":70,"percentage":0.0194759},{"age":71,"percentage":0.0202512},{"age":72,"percentage":0.0215058},{"age":73,"percentage":0.0225030},{"age":74,"percentage":0.0238086},{"age":75,"percentage":0.0250319},{"age":76,"percentage":0.0265030},{"age":77,"percentage":0.0278640},{"age":78,"percentage":0.0296919},{"age":79,"percentage":0.0313687},{"age":80,"percentage":0.0331720},{"age":81,"percentage":0.0346667},{"age":82,"percentage":0.0362878},{"age":83,"percentage":0.0380292},{"age":84,"percentage":0.0398281},{"age":85,"percentage":0.0414046},{"age":86,"percentage":0.0431655},{"age":87,"percentage":0.0448234},{"age":88,"percentage":0.0467222},{"age":89,"percentage":0.0482819},{"age":90,"percentage":0.0507484},{"age":91,"percentage":0.0524728},{"age":92,"percentage":0.0541505},{"age":93,"percentage":0.0560029},{"age":94,"percentage":0.0574670},{"age":95,"percentage":0.0592302},{"age":96,"percentage":0.0603817},{"age":97,"percentage":0.0625077},{"age":98,"percentage":0.0641381},{"age":99,"percentage":0.0665885},{"age":100,"percentage":0.0703413},{"age":101,"percentage":0.0708037},{"age":102,"percentage":0.0746775},{"age":103,"percentage":0.0751893},{"age":104,"percentage":0.0771205},{"age":105,"percentage":0.0759951},{"age":106,"percentage":0.0788962},{"age":107,"percentage":0.0847325},{"age":108,"percentage":0.0869756},{"age":109,"percentage":0.0963563},{"age":110,"percentage":0.1002571},{"age":111,"percentage":0.0748466},{"age":112,"percentage":0.0872211},{"age":113,"percentage":0.0928793},{"age":114,"percentage":0.0970464},{"age":115,"percentage":0.0809249},{"age":116,"percentage":0.0887097},{"age":117,"percentage":0.1666667},{"age":118,"percentage":0.0806452},{"age":119,"percentage":0.0256410},{"age":120,"percentage":0.0697674}],"Kidney Diseases":[{"age":0,"percentage":0.0037501},{"age":1,"percentage":0.0028592},{"age":2,"percentage":0.0025738},{"age":3,"percentage":0.0028249},{"age":4,"percentage":0.0033720},{"age":5,"percentage":0.0040992},{"age":6,"percentage":0.0035781},{"age":7,"percentage":0.0038651},{"age":8,"percentage":0.0042250},{"age":9,"percentage":0.0039273},{"age":10,"percentage":0.0045041},{"age":11,"percentage":0.0042321},{"age":12,"percentage":0.0041404},{"age":13,"percentage":0.0040599},{"age":14,"percentage":0.0035316},{"age":15,"percentage":0.0031351},{"age":16,"percentage":0.0023939},{"age":17,"percentage":0.0020770},{"age":18,"percentage":0.0020451},{"age":19,"percentage":0.0022269},{"age":20,"percentage":0.0027858},{"age":21,"percentage":0.0026183},{"age":22,"percentage":0.0031531},{"age":23,"percentage":0.0034483},{"age":24,"percentage":0.0036068},{"age":25,"percentage":0.0037635},{"age":26,"percentage":0.0039843},{"age":27,"percentage":0.0046013},{"age":28,"percentage":0.0046625},{"age":29,"percentage":0.0051462},{"age":30,"percentage":0.0053519},{"age":31,"percentage":0.0056519},{"age":32,"percentage":0.0056337},{"age":33,"percentage":0.0058758},{"age":34,"percentage":0.0063190},{"age":35,"percentage":0.0064395},{"age":36,"percentage":0.0067339},{"age":37,"percentage":0.0067811},{"age":38,"percentage":0.0073925},{"age":39,"percentage":0.0071162},{"age":40,"percentage":0.0071724},{"age":41,"percentage":0.0071378},{"age":42,"percentage":0.0073449},{"age":43,"percentage":0.0074380},{"age":44,"percentage":0.0075103},{"age":45,"percentage":0.0074733},{"age":46,"percentage":0.0076426},{"age":47,"percentage":0.0078474},{"age":48,"percentage":0.0078582},{"age":49,"percentage":0.0080774},{"age":50,"percentage":0.0079861},{"age":51,"percentage":0.0082577},{"age":52,"percentage":0.0082719},{"age":53,"percentage":0.0084517},{"age":54,"percentage":0.0082179},{"age":55,"percentage":0.0087137},{"age":56,"percentage":0.0087615},{"age":57,"percentage":0.0089224},{"age":58,"percentage":0.0090139},{"age":59,"percentage":0.0091657},{"age":60,"percentage":0.0091220},{"age":61,"percentage":0.0094067},{"age":62,"percentage":0.0095629},{"age":63,"percentage":0.0097793},{"age":64,"percentage":0.0098638},{"age":65,"percentage":0.0101693},{"age":66,"percentage":0.0102261},{"age":67,"percentage":0.0103874},{"age":68,"percentage":0.0105423},{"age":69,"percentage":0.0109766},{"age":70,"percentage":0.0112036},{"age":71,"percentage":0.0114838},{"age":72,"percentage":0.0116512},{"age":73,"percentage":0.0119233},{"age":74,"percentage":0.0122642},{"age":75,"percentage":0.0124613},{"age":76,"percentage":0.0128740},{"age":77,"percentage":0.0130751},{"age":78,"percentage":0.0135026},{"age":79,"percentage":0.0138273},{"age":80,"percentage":0.0140842},{"age":81,"percentage":0.0144346},{"age":82,"percentage":0.0146385},{"age":83,"percentage":0.0149224},{"age":84,"percentage":0.0151008},{"age":85,"percentage":0.0154585},{"age":86,"percentage":0.0157590},{"age":87,"percentage":0.0158586},{"age":88,"percentage":0.0160210},{"age":89,"percentage":0.0160347},{"age":90,"percentage":0.0161303},{"age":91,"percentage":0.0163923},{"age":92,"percentage":0.0161988},{"age":93,"percentage":0.0159689},{"age":94,"percentage":0.0157499},{"age":95,"percentage":0.0159779},{"age":96,"percentage":0.0153103},{"age":97,"percentage":0.0154803},{"age":98,"percentage":0.0149980},{"age":99,"percentage":0.0152488},{"age":100,"percentage":0.0145281},{"age":101,"percentage":0.0144949},{"age":102,"percentage":0.0141373},{"age":103,"percentage":0.0144043},{"age":104,"percentage":0.0130959},{"age":105,"percentage":0.0132828},{"age":106,"percentage":0.0136105},{"age":107,"percentage":0.0135364},{"age":108,"percentage":0.0166923},{"age":109,"percentage":0.0121457},{"age":110,"percentage":0.0218509},{"age":111,"percentage":0.0159509},{"age":112,"percentage":0.0263692},{"age":113,"percentage":0.0154799},{"age":114,"percentage":0.0084388},{"age":115,"percentage":0.0346821},{"age":116,"percentage":0.0080645},{"age":117,"percentage":0.0000000},{"age":118,"percentage":0.0000000},{"age":119,"percentage":0.0000000},{"age":120,"percentage":0.0232558}],"Liver Diseases":[{"age":0,"percentage":0.0003289},{"age":1,"percentage":0.0019207},{"age":2,"percentage":0.0011732},{"age":3,"percentage":0.0010710},{"age":4,"percentage":0.0011303},{"age":5,"percentage":0.0010620},{"age":6,"percentage":0.0010056},{"age":7,"percentage":0.0010039},{"age":8,"percentage":0.0011619},{"age":9,"percentage":0.0014355},{"age":10,"percentage":0.0010100},{"age":11,"percentage":0.0010450},{"age":12,"percentage":0.0011462},{"age":13,"percentage":0.0013209},{"age":14,"percentage":0.0012026},{"age":15,"percentage":0.0011065},{"age":16,"percentage":0.0010793},{"age":17,"percentage":0.0008572},{"age":18,"percentage":0.0007750},{"age":19,"percentage":0.0009796},{"age":20,"percentage":0.0011624},{"age":21,"percentage":0.0016245},{"age":22,"percentage":0.0021538},{"age":23,"percentage":0.0030357},{"age":24,"percentage":0.0039630},{"age":25,"percentage":0.0055662},{"age":26,"percentage":0.0074854},{"age":27,"percentage":0.0095525},{"age":28,"percentage":0.0117911},{"age":29,"percentage":0.0146291},{"age":30,"percentage":0.0179362},{"age":31,"percentage":0.0202364},{"age":32,"percentage":0.0235442},{"age":33,"percentage":0.0265190},{"age":34,"percentage":0.0298091},{"age":35,"percentage":0.0330592},{"age":36,"percentage":0.0353008},{"age":37,"percentage":0.0380562},{"age":38,"percentage":0.0410275},{"age":39,"percentage":0.0427754},{"age":40,"percentage":0.0452969},{"age":41,"percentage":0.0472976},{"age":42,"percentage":0.0483454},{"age":43,"percentage":0.0493348},{"age":44,"percentage":0.0501744},{"age":45,"percentage":0.0499139},{"age":46,"percentage":0.0498637},{"age":47,"percentage":0.0495473},{"age":48,"percentage":0.0492734},{"age":49,"percentage":0.0474161},{"age":50,"percentage":0.0466994},{"age":51,"percentage":0.0449662},{"age":52,"percentage":0.0435532},{"age":53,"percentage":0.0413539},{"age":54,"percentage":0.0397327},{"age":55,"percentage":0.0378562},{"age":56,"percentage":0.0360258},{"age":57,"percentage":0.0336608},{"age":58,"percentage":0.0316108},{"age":59,"percentage":0.0295158},{"age":60,"percentage":0.0272662},{"age":61,"percentage":0.0256873},{"age":62,"percentage":0.0243142},{"age":63,"percentage":0.0229701},{"age":64,"percentage":0.0213121},{"age":65,"percentage":0.0197271},{"age":66,"percentage":0.0179386},{"age":67,"percentage":0.0164006},{"age":68,"percentage":0.0150211},{"age":69,"percentage":0.0138780},{"age":70,"percentage":0.0124596},{"age":71,"percentage":0.0114978},{"age":72,"percentage":0.0106633},{"age":73,"percentage":0.0096652},{"age":74,"percentage":0.0087062},{"age":75,"percentage":0.0079455},{"age":76,"percentage":0.0073200},{"age":77,"percentage":0.0065554},{"age":78,"percentage":0.0059570},{"age":79,"percentage":0.0053026},{"age":80,"percentage":0.0047712},{"age":81,"percentage":0.0042971},{"age":82,"percentage":0.0038225},{"age":83,"percentage":0.0033115},{"age":84,"percentage":0.0029780},{"age":85,"percentage":0.0025977},{"age":86,"percentage":0.0022678},{"age":87,"percentage":0.0019518},{"age":88,"percentage":0.0016987},{"age":89,"percentage":0.0015130},{"age":90,"percentage":0.0012366},{"age":91,"percentage":0.0010065},{"age":92,"percentage":0.0008780},{"age":93,"percentage":0.0007508},{"age":94,"percentage":0.0006581},{"age":95,"percentage":0.0004840},{"age":96,"percentage":0.0004423},{"age":97,"percentage":0.0003495},{"age":98,"percentage":0.0002722},{"age":99,"percentage":0.0003607},{"age":100,"percentage":0.0002375},{"age":101,"percentage":0.0001386},{"age":102,"percentage":0.0001478},{"age":103,"percentage":0.0001155},{"age":104,"percentage":0.0000794},{"age":105,"percentage":0.0002178},{"age":106,"percentage":0.0000748},{"age":107,"percentage":0.0000000},{"age":108,"percentage":0.0006589},{"age":109,"percentage":0.0000000},{"age":110,"percentage":0.0000000},{"age":111,"percentage":0.0000000},{"age":112,"percentage":0.0000000},{"age":113,"percentage":0.0000000},{"age":114,"percentage":0.0000000},{"age":115,"percentage":0.0000000},{"age":116,"percentage":0.0000000},{"age":117,"percentage":0.0000000},{"age":118,"percentage":0.0000000},{"age":119,"percentage":0.0000000},{"age":120,"percentage":0.0000000}],"Motor Vehicle Accidents":[{"age":0,"percentage":0.0030468},{"age":1,"percentage":0.0606615},{"age":2,"percentage":0.1324116},{"age":3,"percentage":0.1651507},{"age":4,"percentage":0.1922577},{"age":5,"percentage":0.2233125},{"age":6,"percentage":0.2448550},{"age":7,"percentage":0.2476910},{"age":8,"percentage":0.2430156},{"age":9,"percentage":0.2358549},{"age":10,"percentage":0.2267355},{"age":11,"percentage":0.2226547},{"age":12,"percentage":0.2238596},{"age":13,"percentage":0.2323860},{"age":14,"percentage":0.2622502},{"age":15,"percentage":0.3039454},{"age":16,"percentage":0.3922097},{"age":17,"percentage":0.4021877},{"age":18,"percentage":0.4083656},{"age":19,"percentage":0.3772022},{"age":20,"percentage":0.3476631},{"age":21,"percentage":0.3346122},{"age":22,"percentage":0.3094536},{"age":23,"percentage":0.2852441},{"age":24,"percentage":0.2633126},{"age":25,"percentage":0.2434065},{"age":26,"percentage":0.2243311},{"age":27,"percentage":0.2064623},{"age":28,"percentage":0.1914370},{"age":29,"percentage":0.1768545},{"age":30,"percentage":0.1618201},{"age":31,"percentage":0.1512807},{"age":32,"percentage":0.1394724},{"age":33,"percentage":0.1288242},{"age":34,"percentage":0.1186280},{"age":35,"percentage":0.1096055},{"age":36,"percentage":0.1029908},{"age":37,"percentage":0.0941130},{"age":38,"percentage":0.0875938},{"age":39,"percentage":0.0808027},{"age":40,"percentage":0.0742042},{"age":41,"percentage":0.0681980},{"age":42,"percentage":0.0628626},{"age":43,"percentage":0.0569118},{"age":44,"percentage":0.0522101},{"age":45,"percentage":0.0483947},{"age":46,"percentage":0.0440226},{"age":47,"percentage":0.0400574},{"age":48,"percentage":0.0364694},{"age":49,"percentage":0.0338163},{"age":50,"percentage":0.0309800},{"age":51,"percentage":0.0283822},{"age":52,"percentage":0.0261647},{"age":53,"percentage":0.0239210},{"age":54,"percentage":0.0220818},{"age":55,"percentage":0.0203735},{"age":56,"percentage":0.0187272},{"age":57,"percentage":0.0171468},{"age":58,"percentage":0.0156569},{"age":59,"percentage":0.0145681},{"age":60,"percentage":0.0134988},{"age":61,"percentage":0.0123106},{"age":62,"percentage":0.0115502},{"age":63,"percentage":0.0105698},{"age":64,"percentage":0.0098620},{"age":65,"percentage":0.0091880},{"age":66,"percentage":0.0085957},{"age":67,"percentage":0.0081508},{"age":68,"percentage":0.0077905},{"age":69,"percentage":0.0072949},{"age":70,"percentage":0.0068982},{"age":71,"percentage":0.0066923},{"age":72,"percentage":0.0064231},{"age":73,"percentage":0.0061350},{"age":74,"percentage":0.0059635},{"age":75,"percentage":0.0056658},{"age":76,"percentage":0.0055483},{"age":77,"percentage":0.0053004},{"age":78,"percentage":0.0050741},{"age":79,"percentage":0.0047819},{"age":80,"percentage":0.0044747},{"age":81,"percentage":0.0041417},{"age":82,"percentage":0.0039819},{"age":83,"percentage":0.0035959},{"age":84,"percentage":0.0033324},{"age":85,"percentage":0.0030569},{"age":86,"percentage":0.0027407},{"age":87,"percentage":0.0023978},{"age":88,"percentage":0.0021383},{"age":89,"percentage":0.0018828},{"age":90,"percentage":0.0016029},{"age":91,"percentage":0.0014347},{"age":92,"percentage":0.0012243},{"age":93,"percentage":0.0010621},{"age":94,"percentage":0.0008345},{"age":95,"percentage":0.0006703},{"age":96,"percentage":0.0006092},{"age":97,"percentage":0.0004853},{"age":98,"percentage":0.0004156},{"age":99,"percentage":0.0004720},{"age":100,"percentage":0.0003278},{"age":101,"percentage":0.0004159},{"age":102,"percentage":0.0002640},{"age":103,"percentage":0.0001485},{"age":104,"percentage":0.0001587},{"age":105,"percentage":0.0001742},{"age":106,"percentage":0.0006730},{"age":107,"percentage":0.0002603},{"age":108,"percentage":0.0010982},{"age":109,"percentage":0.0012146},{"age":110,"percentage":0.0012853},{"age":111,"percentage":0.0012270},{"age":112,"percentage":0.0000000},{"age":113,"percentage":0.0030960},{"age":114,"percentage":0.0000000},{"age":115,"percentage":0.0000000},{"age":116,"percentage":0.0000000},{"age":117,"percentage":0.0277778},{"age":118,"percentage":0.0000000},{"age":119,"percentage":0.0000000},{"age":120,"percentage":0.0000000}],"Other Infectious Diseases":[{"age":0,"percentage":0.0189130},{"age":1,"percentage":0.0467060},{"age":2,"percentage":0.0379123},{"age":3,"percentage":0.0327663},{"age":4,"percentage":0.0312518},{"age":5,"percentage":0.0296292},{"age":6,"percentage":0.0285080},{"age":7,"percentage":0.0264783},{"age":8,"percentage":0.0245577},{"age":9,"percentage":0.0235909},{"age":10,"percentage":0.0203096},{"age":11,"percentage":0.0189921},{"age":12,"percentage":0.0185497},{"age":13,"percentage":0.0160065},{"age":14,"percentage":0.0134718},{"age":15,"percentage":0.0110767},{"age":16,"percentage":0.0084638},{"age":17,"percentage":0.0079584},{"age":18,"percentage":0.0071579},{"age":19,"percentage":0.0073572},{"age":20,"percentage":0.0080718},{"age":21,"percentage":0.0082706},{"age":22,"percentage":0.0108710},{"age":23,"percentage":0.0139257},{"age":24,"percentage":0.0182168},{"age":25,"percentage":0.0245713},{"age":26,"percentage":0.0308737},{"age":27,"percentage":0.0387105},{"age":28,"percentage":0.0463071},{"age":29,"percentage":0.0542030},{"age":30,"percentage":0.0604021},{"age":31,"percentage":0.0668689},{"age":32,"percentage":0.0698065},{"age":33,"percentage":0.0723395},{"age":34,"percentage":0.0710748},{"age":35,"percentage":0.0696292},{"age":36,"percentage":0.0663275},{"age":37,"percentage":0.0639788},{"age":38,"percentage":0.0587224},{"age":39,"percentage":0.0537304},{"age":40,"percentage":0.0494425},{"age":41,"percentage":0.0448333},{"age":42,"percentage":0.0397444},{"age":43,"percentage":0.0340509},{"age":44,"percentage":0.0303116},{"age":45,"percentage":0.0266195},{"age":46,"percentage":0.0228411},{"age":47,"percentage":0.0201925},{"age":48,"percentage":0.0170640},{"age":49,"percentage":0.0149971},{"age":50,"percentage":0.0131458},{"age":51,"percentage":0.0117814},{"age":52,"percentage":0.0105945},{"age":53,"percentage":0.0098288},{"age":54,"percentage":0.0090155},{"age":55,"percentage":0.0083346},{"age":56,"percentage":0.0078943},{"age":57,"percentage":0.0076086},{"age":58,"percentage":0.0072978},{"age":59,"percentage":0.0070959},{"age":60,"percentage":0.0068713},{"age":61,"percentage":0.0067901},{"age":62,"percentage":0.0066440},{"age":63,"percentage":0.0064602},{"age":64,"percentage":0.0064332},{"age":65,"percentage":0.0064649},{"age":66,"percentage":0.0063066},{"age":67,"percentage":0.0062191},{"age":68,"percentage":0.0061941},{"age":69,"percentage":0.0063827},{"age":70,"percentage":0.0061572},{"age":71,"percentage":0.0061656},{"age":72,"percentage":0.0061434},{"age":73,"percentage":0.0062057},{"age":74,"percentage":0.0060719},{"age":75,"percentage":0.0061518},{"age":76,"percentage":0.0060926},{"age":77,"percentage":0.0059225},{"age":78,"percentage":0.0060305},{"age":79,"percentage":0.0059008},{"age":80,"percentage":0.0057621},{"age":81,"percentage":0.0058229},{"age":82,"percentage":0.0057194},{"age":83,"percentage":0.0057378},{"age":84,"percentage":0.0056881},{"age":85,"percentage":0.0056067},{"age":86,"percentage":0.0056373},{"age":87,"percentage":0.0055116},{"age":88,"percentage":0.0053842},{"age":89,"percentage":0.0054356},{"age":90,"percentage":0.0052655},{"age":91,"percentage":0.0051273},{"age":92,"percentage":0.0052283},{"age":93,"percentage":0.0050147},{"age":94,"percentage":0.0049864},{"age":95,"percentage":0.0049008},{"age":96,"percentage":0.0048985},{"age":97,"percentage":0.0049126},{"age":98,"percentage":0.0049386},{"age":99,"percentage":0.0047773},{"age":100,"percentage":0.0049266},{"age":101,"percentage":0.0046375},{"age":102,"percentage":0.0049517},{"age":103,"percentage":0.0048839},{"age":104,"percentage":0.0047357},{"age":105,"percentage":0.0048341},{"age":106,"percentage":0.0054592},{"age":107,"percentage":0.0063777},{"age":108,"percentage":0.0054909},{"age":109,"percentage":0.0101215},{"age":110,"percentage":0.0070694},{"age":111,"percentage":0.0073620},{"age":112,"percentage":0.0182556},{"age":113,"percentage":0.0092879},{"age":114,"percentage":0.0168776},{"age":115,"percentage":0.0057803},{"age":116,"percentage":0.0161290},{"age":117,"percentage":0.0138889},{"age":118,"percentage":0.0161290},{"age":119,"percentage":0.0000000},{"age":120,"percentage":0.0465116}],"Perinatal Complications":[{"age":0,"percentage":0.5385683},{"age":1,"percentage":0.0338751},{"age":2,"percentage":0.0076016},{"age":3,"percentage":0.0050135},{"age":4,"percentage":0.0036922},{"age":5,"percentage":0.0034620},{"age":6,"percentage":0.0030636},{"age":7,"percentage":0.0030870},{"age":8,"percentage":0.0029047},{"age":9,"percentage":0.0026814},{"age":10,"percentage":0.0021838},{"age":11,"percentage":0.0019332},{"age":12,"percentage":0.0016140},{"age":13,"percentage":0.0011849},{"age":14,"percentage":0.0011569},{"age":15,"percentage":0.0007492},{"age":16,"percentage":0.0005437},{"age":17,"percentage":0.0004484},{"age":18,"percentage":0.0002099},{"age":19,"percentage":0.0002777},{"age":20,"percentage":0.0002255},{"age":21,"percentage":0.0002007},{"age":22,"percentage":0.0001698},{"age":23,"percentage":0.0001817},{"age":24,"percentage":0.0001336},{"age":25,"percentage":0.0001580},{"age":26,"percentage":0.0001430},{"age":27,"percentage":0.0001263},{"age":28,"percentage":0.0001156},{"age":29,"percentage":0.0001497},{"age":30,"percentage":0.0001405},{"age":31,"percentage":0.0000574},{"age":32,"percentage":0.0000724},{"age":33,"percentage":0.0000903},{"age":34,"percentage":0.0000392},{"age":35,"percentage":0.0000709},{"age":36,"percentage":0.0000645},{"age":37,"percentage":0.0000813},{"age":38,"percentage":0.0000734},{"age":39,"percentage":0.0000570},{"age":40,"percentage":0.0000474},{"age":41,"percentage":0.0000473},{"age":42,"percentage":0.0000364},{"age":43,"percentage":0.0000364},{"age":44,"percentage":0.0000341},{"age":45,"percentage":0.0000415},{"age":46,"percentage":0.0000239},{"age":47,"percentage":0.0000290},{"age":48,"percentage":0.0000175},{"age":49,"percentage":0.0000103},{"age":50,"percentage":0.0000165},{"age":51,"percentage":0.0000129},{"age":52,"percentage":0.0000084},{"age":53,"percentage":0.0000125},{"age":54,"percentage":0.0000149},{"age":55,"percentage":0.0000121},{"age":56,"percentage":0.0000104},{"age":57,"percentage":0.0000107},{"age":58,"percentage":0.0000034},{"age":59,"percentage":0.0000080},{"age":60,"percentage":0.0000067},{"age":61,"percentage":0.0000043},{"age":62,"percentage":0.0000013},{"age":63,"percentage":0.0000077},{"age":64,"percentage":0.0000036},{"age":65,"percentage":0.0000017},{"age":66,"percentage":0.0000050},{"age":67,"percentage":0.0000058},{"age":68,"percentage":0.0000056},{"age":69,"percentage":0.0000029},{"age":70,"percentage":0.0000023},{"age":71,"percentage":0.0000023},{"age":72,"percentage":0.0000047},{"age":73,"percentage":0.0000067},{"age":74,"percentage":0.0000057},{"age":75,"percentage":0.0000012},{"age":76,"percentage":0.0000015},{"age":77,"percentage":0.0000034},{"age":78,"percentage":0.0000015},{"age":79,"percentage":0.0000007},{"age":80,"percentage":0.0000018},{"age":81,"percentage":0.0000011},{"age":82,"percentage":0.0000007},{"age":83,"percentage":0.0000010},{"age":84,"percentage":0.0000028},{"age":85,"percentage":0.0000007},{"age":86,"percentage":0.0000026},{"age":87,"percentage":0.0000028},{"age":88,"percentage":0.0000008},{"age":89,"percentage":0.0000005},{"age":90,"percentage":0.0000030},{"age":91,"percentage":0.0000011},{"age":92,"percentage":0.0000000},{"age":93,"percentage":0.0000007},{"age":94,"percentage":0.0000009},{"age":95,"percentage":0.0000000},{"age":96,"percentage":0.0000014},{"age":97,"percentage":0.0000018},{"age":98,"percentage":0.0000000},{"age":99,"percentage":0.0000067},{"age":100,"percentage":0.0000048},{"age":101,"percentage":0.0000485},{"age":102,"percentage":0.0000317},{"age":103,"percentage":0.0000000},{"age":104,"percentage":0.0000000},{"age":105,"percentage":0.0000000},{"age":106,"percentage":0.0000000},{"age":107,"percentage":0.0000000},{"age":108,"percentage":0.0000000},{"age":109,"percentage":0.0000000},{"age":110,"percentage":0.0000000},{"age":111,"percentage":0.0000000},{"age":112,"percentage":0.0000000},{"age":113,"percentage":0.0000000},{"age":114,"percentage":0.0000000},{"age":115,"percentage":0.0000000},{"age":116,"percentage":0.0000000},{"age":117,"percentage":0.0000000},{"age":118,"percentage":0.0000000},{"age":119,"percentage":0.0000000},{"age":120,"percentage":0.0000000}],"Pregnancy Complications":[{"age":0,"percentage":0.0000006},{"age":1,"percentage":0.0000000},{"age":2,"percentage":0.0000000},{"age":3,"percentage":0.0000000},{"age":4,"percentage":0.0000000},{"age":5,"percentage":0.0000000},{"age":6,"percentage":0.0000000},{"age":7,"percentage":0.0000000},{"age":8,"percentage":0.0000000},{"age":9,"percentage":0.0000000},{"age":10,"percentage":0.0000273},{"age":11,"percentage":0.0000522},{"age":12,"percentage":0.0000936},{"age":13,"percentage":0.0002914},{"age":14,"percentage":0.0007459},{"age":15,"percentage":0.0013947},{"age":16,"percentage":0.0018827},{"age":17,"percentage":0.0024396},{"age":18,"percentage":0.0029116},{"age":19,"percentage":0.0035549},{"age":20,"percentage":0.0039432},{"age":21,"percentage":0.0041807},{"age":22,"percentage":0.0045066},{"age":23,"percentage":0.0046665},{"age":24,"percentage":0.0048090},{"age":25,"percentage":0.0050032},{"age":26,"percentage":0.0049854},{"age":27,"percentage":0.0054079},{"age":28,"percentage":0.0052405},{"age":29,"percentage":0.0050619},{"age":30,"percentage":0.0046902},{"age":31,"percentage":0.0045568},{"age":32,"percentage":0.0043520},{"age":33,"percentage":0.0040458},{"age":34,"percentage":0.0036540},{"age":35,"percentage":0.0034287},{"age":36,"percentage":0.0030657},{"age":37,"percentage":0.0026305},{"age":38,"percentage":0.0022781},{"age":39,"percentage":0.0019089},{"age":40,"percentage":0.0015232},{"age":41,"percentage":0.0011598},{"age":42,"percentage":0.0008601},{"age":43,"percentage":0.0006515},{"age":44,"percentage":0.0004067},{"age":45,"percentage":0.0002532},{"age":46,"percentage":0.0002339},{"age":47,"percentage":0.0002337},{"age":48,"percentage":0.0002073},{"age":49,"percentage":0.0001789},{"age":50,"percentage":0.0001718},{"age":51,"percentage":0.0001385},{"age":52,"percentage":0.0001629},{"age":53,"percentage":0.0001591},{"age":54,"percentage":0.0001388},{"age":55,"percentage":0.0000090},{"age":56,"percentage":0.0000057},{"age":57,"percentage":0.0000080},{"age":58,"percentage":0.0000017},{"age":59,"percentage":0.0000024},{"age":60,"percentage":0.0000022},{"age":61,"percentage":0.0000014},{"age":62,"percentage":0.0000000},{"age":63,"percentage":0.0000006},{"age":64,"percentage":0.0000018},{"age":65,"percentage":0.0000017},{"age":66,"percentage":0.0000011},{"age":67,"percentage":0.0000016},{"age":68,"percentage":0.0000005},{"age":69,"percentage":0.0000005},{"age":70,"percentage":0.0000005},{"age":71,"percentage":0.0000000},{"age":72,"percentage":0.0000004},{"age":73,"percentage":0.0000000},{"age":74,"percentage":0.0000000},{"age":75,"percentage":0.0000004},{"age":76,"percentage":0.0000000},{"age":77,"percentage":0.0000007},{"age":78,"percentage":0.0000007},{"age":79,"percentage":0.0000000},{"age":80,"percentage":0.0000004},{"age":81,"percentage":0.0000000},{"age":82,"percentage":0.0000000},{"age":83,"percentage":0.0000000},{"age":84,"percentage":0.0000000},{"age":85,"percentage":0.0000000},{"age":86,"percentage":0.0000000},{"age":87,"percentage":0.0000000},{"age":88,"percentage":0.0000000},{"age":89,"percentage":0.0000000},{"age":90,"percentage":0.0000000},{"age":91,"percentage":0.0000000},{"age":92,"percentage":0.0000006},{"age":93,"percentage":0.0000007},{"age":94,"percentage":0.0000009},{"age":95,"percentage":0.0000000},{"age":96,"percentage":0.0000000},{"age":97,"percentage":0.0000000},{"age":98,"percentage":0.0000000},{"age":99,"percentage":0.0000034},{"age":100,"percentage":0.0000000},{"age":101,"percentage":0.0000000},{"age":102,"percentage":0.0000000},{"age":103,"percentage":0.0000000},{"age":104,"percentage":0.0000000},{"age":105,"percentage":0.0000000},{"age":106,"percentage":0.0000000},{"age":107,"percentage":0.0000000},{"age":108,"percentage":0.0000000},{"age":109,"percentage":0.0000000},{"age":110,"percentage":0.0000000},{"age":111,"percentage":0.0000000},{"age":112,"percentage":0.0000000},{"age":113,"percentage":0.0000000},{"age":114,"percentage":0.0000000},{"age":115,"percentage":0.0000000},{"age":116,"percentage":0.0000000},{"age":117,"percentage":0.0000000},{"age":118,"percentage":0.0000000},{"age":119,"percentage":0.0000000},{"age":120,"percentage":0.0000000}],"Stroke":[{"age":0,"percentage":0.0034961},{"age":1,"percentage":0.0094885},{"age":2,"percentage":0.0091100},{"age":3,"percentage":0.0086145},{"age":4,"percentage":0.0087595},{"age":5,"percentage":0.0096640},{"age":6,"percentage":0.0099626},{"age":7,"percentage":0.0112689},{"age":8,"percentage":0.0131503},{"age":9,"percentage":0.0140841},{"age":10,"percentage":0.0151503},{"age":11,"percentage":0.0141592},{"age":12,"percentage":0.0143392},{"age":13,"percentage":0.0139474},{"age":14,"percentage":0.0111427},{"age":15,"percentage":0.0094630},{"age":16,"percentage":0.0072710},{"age":17,"percentage":0.0067848},{"age":18,"percentage":0.0064098},{"age":19,"percentage":0.0065846},{"age":20,"percentage":0.0071599},{"age":21,"percentage":0.0077116},{"age":22,"percentage":0.0081933},{"age":23,"percentage":0.0092838},{"age":24,"percentage":0.0105877},{"age":25,"percentage":0.0110336},{"age":26,"percentage":0.0118544},{"age":27,"percentage":0.0136145},{"age":28,"percentage":0.0147774},{"age":29,"percentage":0.0157145},{"age":30,"percentage":0.0175193},{"age":31,"percentage":0.0183289},{"age":32,"percentage":0.0206485},{"age":33,"percentage":0.0214392},{"age":34,"percentage":0.0232978},{"age":35,"percentage":0.0254781},{"age":36,"percentage":0.0266558},{"age":37,"percentage":0.0280893},{"age":38,"percentage":0.0297935},{"age":39,"percentage":0.0313913},{"age":40,"percentage":0.0328882},{"age":41,"percentage":0.0342450},{"age":42,"percentage":0.0358229},{"age":43,"percentage":0.0370353},{"age":44,"percentage":0.0380348},{"age":45,"percentage":0.0387078},{"age":46,"percentage":0.0392702},{"age":47,"percentage":0.0396635},{"age":48,"percentage":0.0404168},{"age":49,"percentage":0.0407774},{"age":50,"percentage":0.0410698},{"age":51,"percentage":0.0411952},{"age":52,"percentage":0.0419014},{"age":53,"percentage":0.0416538},{"age":54,"percentage":0.0417592},{"age":55,"percentage":0.0421356},{"age":56,"percentage":0.0423486},{"age":57,"percentage":0.0428572},{"age":58,"percentage":0.0434854},{"age":59,"percentage":0.0442322},{"age":60,"percentage":0.0450616},{"age":61,"percentage":0.0462798},{"age":62,"percentage":0.0477222},{"age":63,"percentage":0.0490315},{"age":64,"percentage":0.0503365},{"age":65,"percentage":0.0524919},{"age":66,"percentage":0.0539562},{"age":67,"percentage":0.0563417},{"age":68,"percentage":0.0585085},{"age":69,"percentage":0.0608367},{"age":70,"percentage":0.0639358},{"age":71,"percentage":0.0666872},{"age":72,"percentage":0.0698137},{"age":73,"percentage":0.0725618},{"age":74,"percentage":0.0760409},{"age":75,"percentage":0.0794070},{"age":76,"percentage":0.0821804},{"age":77,"percentage":0.0854467},{"age":78,"percentage":0.0888573},{"age":79,"percentage":0.0921831},{"age":80,"percentage":0.0950526},{"age":81,"percentage":0.0973013},{"age":82,"percentage":0.1000821},{"age":83,"percentage":0.1025456},{"age":84,"percentage":0.1045389},{"age":85,"percentage":0.1058901},{"age":86,"percentage":0.1069561},{"age":87,"percentage":0.1077380},{"age":88,"percentage":0.1083266},{"age":89,"percentage":0.1086831},{"age":90,"percentage":0.1077968},{"age":91,"percentage":0.1074301},{"age":92,"percentage":0.1063029},{"age":93,"percentage":0.1052470},{"age":94,"percentage":0.1038732},{"age":95,"percentage":0.1017207},{"age":96,"percentage":0.1004878},{"age":97,"percentage":0.0977434},{"age":98,"percentage":0.0967637},{"age":99,"percentage":0.0930438},{"age":100,"percentage":0.0877485},{"age":101,"percentage":0.0866572},{"age":102,"percentage":0.0840530},{"age":103,"percentage":0.0804033},{"age":104,"percentage":0.0789195},{"age":105,"percentage":0.0789130},{"age":106,"percentage":0.0773258},{"age":107,"percentage":0.0805675},{"age":108,"percentage":0.0683066},{"age":109,"percentage":0.0732794},{"age":110,"percentage":0.0732648},{"age":111,"percentage":0.0932515},{"age":112,"percentage":0.0993915},{"age":113,"percentage":0.1145511},{"age":114,"percentage":0.0970464},{"age":115,"percentage":0.1098266},{"age":116,"percentage":0.0967742},{"age":117,"percentage":0.1111111},{"age":118,"percentage":0.0806452},{"age":119,"percentage":0.1025641},{"age":120,"percentage":0.1162791}],"Suicide":[{"age":0,"percentage":0.0000000},{"age":1,"percentage":0.0000000},{"age":2,"percentage":0.0000000},{"age":3,"percentage":0.0000000},{"age":4,"percentage":0.0000000},{"age":5,"percentage":0.0001912},{"age":6,"percentage":0.0003040},{"age":7,"percentage":0.0004267},{"age":8,"percentage":0.0010827},{"age":9,"percentage":0.0031689},{"age":10,"percentage":0.0083804},{"age":11,"percentage":0.0187309},{"age":12,"percentage":0.0352515},{"age":13,"percentage":0.0600245},{"age":14,"percentage":0.0821244},{"age":15,"percentage":0.0960016},{"age":16,"percentage":0.0997566},{"age":17,"percentage":0.1023651},{"age":18,"percentage":0.1039993},{"age":19,"percentage":0.1138929},{"age":20,"percentage":0.1188222},{"age":21,"percentage":0.1281104},{"age":22,"percentage":0.1300644},{"age":23,"percentage":0.1327783},{"age":24,"percentage":0.1334250},{"age":25,"percentage":0.1318651},{"age":26,"percentage":0.1304131},{"age":27,"percentage":0.1277246},{"age":28,"percentage":0.1258200},{"age":29,"percentage":0.1211825},{"age":30,"percentage":0.1166216},{"age":31,"percentage":0.1133557},{"age":32,"percentage":0.1060702},{"age":33,"percentage":0.1034787},{"age":34,"percentage":0.0993807},{"age":35,"percentage":0.0944917},{"age":36,"percentage":0.0895912},{"age":37,"percentage":0.0853310},{"age":38,"percentage":0.0804565},{"age":39,"percentage":0.0767118},{"age":40,"percentage":0.0721035},{"age":41,"percentage":0.0670750},{"age":42,"percentage":0.0624763},{"age":43,"percentage":0.0576955},{"age":44,"percentage":0.0549527},{"age":45,"percentage":0.0503352},{"age":46,"percentage":0.0467691},{"age":47,"percentage":0.0437296},{"age":48,"percentage":0.0404089},{"age":49,"percentage":0.0374890},{"age":50,"percentage":0.0341335},{"age":51,"percentage":0.0315252},{"age":52,"percentage":0.0290821},{"age":53,"percentage":0.0265822},{"age":54,"percentage":0.0246624},{"age":55,"percentage":0.0225011},{"age":56,"percentage":0.0205798},{"age":57,"percentage":0.0186667},{"age":58,"percentage":0.0171154},{"age":59,"percentage":0.0157792},{"age":60,"percentage":0.0141093},{"age":61,"percentage":0.0126703},{"age":62,"percentage":0.0108134},{"age":63,"percentage":0.0099943},{"age":64,"percentage":0.0093296},{"age":65,"percentage":0.0084834},{"age":66,"percentage":0.0079481},{"age":67,"percentage":0.0074280},{"age":68,"percentage":0.0070872},{"age":69,"percentage":0.0064907},{"age":70,"percentage":0.0060666},{"age":71,"percentage":0.0057046},{"age":72,"percentage":0.0053524},{"age":73,"percentage":0.0051632},{"age":74,"percentage":0.0046526},{"age":75,"percentage":0.0045638},{"age":76,"percentage":0.0042493},{"age":77,"percentage":0.0039857},{"age":78,"percentage":0.0036510},{"age":79,"percentage":0.0034311},{"age":80,"percentage":0.0031880},{"age":81,"percentage":0.0029492},{"age":82,"percentage":0.0027610},{"age":83,"percentage":0.0025295},{"age":84,"percentage":0.0022771},{"age":85,"percentage":0.0021378},{"age":86,"percentage":0.0018765},{"age":87,"percentage":0.0016854},{"age":88,"percentage":0.0015194},{"age":89,"percentage":0.0013470},{"age":90,"percentage":0.0011778},{"age":91,"percentage":0.0010251},{"age":92,"percentage":0.0008895},{"age":93,"percentage":0.0007725},{"age":94,"percentage":0.0006590},{"age":95,"percentage":0.0005722},{"age":96,"percentage":0.0004604},{"age":97,"percentage":0.0004110},{"age":98,"percentage":0.0003232},{"age":99,"percentage":0.0003237},{"age":100,"percentage":0.0002185},{"age":101,"percentage":0.0001941},{"age":102,"percentage":0.0001584},{"age":103,"percentage":0.0000825},{"age":104,"percentage":0.0000265},{"age":105,"percentage":0.0001307},{"age":106,"percentage":0.0000000},{"age":107,"percentage":0.0000000},{"age":108,"percentage":0.0000000},{"age":109,"percentage":0.0004049},{"age":110,"percentage":0.0000000},{"age":111,"percentage":0.0000000},{"age":112,"percentage":0.0000000},{"age":113,"percentage":0.0000000},{"age":114,"percentage":0.0000000},{"age":115,"percentage":0.0000000},{"age":116,"percentage":0.0000000},{"age":117,"percentage":0.0000000},{"age":118,"percentage":0.0000000},{"age":119,"percentage":0.0000000},{"age":120,"percentage":0.0000000}],"Tuberculosis":[{"age":0,"percentage":0.0000431},{"age":1,"percentage":0.0008435},{"age":2,"percentage":0.0012450},{"age":3,"percentage":0.0009779},{"age":4,"percentage":0.0005840},{"age":5,"percentage":0.0006797},{"age":6,"percentage":0.0005145},{"age":7,"percentage":0.0005020},{"age":8,"percentage":0.0003433},{"age":9,"percentage":0.0005688},{"age":10,"percentage":0.0004095},{"age":11,"percentage":0.0004180},{"age":12,"percentage":0.0004912},{"age":13,"percentage":0.0003108},{"age":14,"percentage":0.0003044},{"age":15,"percentage":0.0004149},{"age":16,"percentage":0.0002597},{"age":17,"percentage":0.0003758},{"age":18,"percentage":0.0003068},{"age":19,"percentage":0.0003434},{"age":20,"percentage":0.0004459},{"age":21,"percentage":0.0005638},{"age":22,"percentage":0.0006549},{"age":23,"percentage":0.0007270},{"age":24,"percentage":0.0007520},{"age":25,"percentage":0.0009236},{"age":26,"percentage":0.0009517},{"age":27,"percentage":0.0012536},{"age":28,"percentage":0.0012523},{"age":29,"percentage":0.0014222},{"age":30,"percentage":0.0014864},{"age":31,"percentage":0.0015189},{"age":32,"percentage":0.0017118},{"age":33,"percentage":0.0016864},{"age":34,"percentage":0.0017819},{"age":35,"percentage":0.0017572},{"age":36,"percentage":0.0018143},{"age":37,"percentage":0.0019297},{"age":38,"percentage":0.0019750},{"age":39,"percentage":0.0018398},{"age":40,"percentage":0.0018524},{"age":41,"percentage":0.0018173},{"age":42,"percentage":0.0019219},{"age":43,"percentage":0.0017587},{"age":44,"percentage":0.0018036},{"age":45,"percentage":0.0017783},{"age":46,"percentage":0.0016965},{"age":47,"percentage":0.0017431},{"age":48,"percentage":0.0016571},{"age":49,"percentage":0.0016575},{"age":50,"percentage":0.0015884},{"age":51,"percentage":0.0015262},{"age":52,"percentage":0.0015709},{"age":53,"percentage":0.0014556},{"age":54,"percentage":0.0014136},{"age":55,"percentage":0.0014278},{"age":56,"percentage":0.0014049},{"age":57,"percentage":0.0013396},{"age":58,"percentage":0.0013340},{"age":59,"percentage":0.0012565},{"age":60,"percentage":0.0012540},{"age":61,"percentage":0.0012058},{"age":62,"percentage":0.0011812},{"age":63,"percentage":0.0011561},{"age":64,"percentage":0.0010958},{"age":65,"percentage":0.0011152},{"age":66,"percentage":0.0011120},{"age":67,"percentage":0.0011003},{"age":68,"percentage":0.0010136},{"age":69,"percentage":0.0009660},{"age":70,"percentage":0.0009348},{"age":71,"percentage":0.0009204},{"age":72,"percentage":0.0008859},{"age":73,"percentage":0.0008949},{"age":74,"percentage":0.0008471},{"age":75,"percentage":0.0008213},{"age":76,"percentage":0.0008186},{"age":77,"percentage":0.0007459},{"age":78,"percentage":0.0007308},{"age":79,"percentage":0.0007032},{"age":80,"percentage":0.0006865},{"age":81,"percentage":0.0006547},{"age":82,"percentage":0.0006315},{"age":83,"percentage":0.0006073},{"age":84,"percentage":0.0005756},{"age":85,"percentage":0.0005472},{"age":86,"percentage":0.0005217},{"age":87,"percentage":0.0004618},{"age":88,"percentage":0.0004312},{"age":89,"percentage":0.0004021},{"age":90,"percentage":0.0003553},{"age":91,"percentage":0.0003325},{"age":92,"percentage":0.0003176},{"age":93,"percentage":0.0002687},{"age":94,"percentage":0.0002462},{"age":95,"percentage":0.0002271},{"age":96,"percentage":0.0002323},{"age":97,"percentage":0.0001974},{"age":98,"percentage":0.0002114},{"age":99,"percentage":0.0001618},{"age":100,"percentage":0.0001473},{"age":101,"percentage":0.0001594},{"age":102,"percentage":0.0001056},{"age":103,"percentage":0.0000990},{"age":104,"percentage":0.0002381},{"age":105,"percentage":0.0000871},{"age":106,"percentage":0.0003739},{"age":107,"percentage":0.0001302},{"age":108,"percentage":0.0000000},{"age":109,"percentage":0.0004049},{"age":110,"percentage":0.0000000},{"age":111,"percentage":0.0012270},{"age":112,"percentage":0.0020284},{"age":113,"percentage":0.0000000},{"age":114,"percentage":0.0000000},{"age":115,"percentage":0.0000000},{"age":116,"percentage":0.0000000},{"age":117,"percentage":0.0000000},{"age":118,"percentage":0.0000000},{"age":119,"percentage":0.0000000},{"age":120,"percentage":0.0000000}],"Undetermined Diseases":[{"age":0,"percentage":0.1131091},{"age":1,"percentage":0.1129117},{"age":2,"percentage":0.0341414},{"age":3,"percentage":0.0240120},{"age":4,"percentage":0.0199115},{"age":5,"percentage":0.0182872},{"age":6,"percentage":0.0155753},{"age":7,"percentage":0.0139544},{"age":8,"percentage":0.0155268},{"age":9,"percentage":0.0157092},{"age":10,"percentage":0.0163241},{"age":11,"percentage":0.0164842},{"age":12,"percentage":0.0161170},{"age":13,"percentage":0.0169001},{"age":14,"percentage":0.0173839},{"age":15,"percentage":0.0173584},{"age":16,"percentage":0.0168303},{"age":17,"percentage":0.0166422},{"age":18,"percentage":0.0181961},{"age":19,"percentage":0.0194105},{"age":20,"percentage":0.0216300},{"age":21,"percentage":0.0218494},{"age":22,"percentage":0.0239202},{"age":23,"percentage":0.0249386},{"age":24,"percentage":0.0253759},{"age":25,"percentage":0.0265666},{"age":26,"percentage":0.0278164},{"age":27,"percentage":0.0283417},{"age":28,"percentage":0.0277871},{"age":29,"percentage":0.0283413},{"age":30,"percentage":0.0293469},{"age":31,"percentage":0.0275927},{"age":32,"percentage":0.0279515},{"age":33,"percentage":0.0279715},{"age":34,"percentage":0.0269911},{"age":35,"percentage":0.0273212},{"age":36,"percentage":0.0269821},{"age":37,"percentage":0.0255536},{"age":38,"percentage":0.0249534},{"age":39,"percentage":0.0240829},{"age":40,"percentage":0.0239666},{"age":41,"percentage":0.0220787},{"age":42,"percentage":0.0213470},{"age":43,"percentage":0.0207718},{"age":44,"percentage":0.0196158},{"age":45,"percentage":0.0191165},{"age":46,"percentage":0.0177866},{"age":47,"percentage":0.0170013},{"age":48,"percentage":0.0166222},{"age":49,"percentage":0.0155131},{"age":50,"percentage":0.0148112},{"age":51,"percentage":0.0140273},{"age":52,"percentage":0.0135710},{"age":53,"percentage":0.0127320},{"age":54,"percentage":0.0124449},{"age":55,"percentage":0.0121656},{"age":56,"percentage":0.0113639},{"age":57,"percentage":0.0110251},{"age":58,"percentage":0.0107367},{"age":59,"percentage":0.0104055},{"age":60,"percentage":0.0103054},{"age":61,"percentage":0.0098187},{"age":62,"percentage":0.0097944},{"age":63,"percentage":0.0095815},{"age":64,"percentage":0.0094917},{"age":65,"percentage":0.0092758},{"age":66,"percentage":0.0086386},{"age":67,"percentage":0.0086935},{"age":68,"percentage":0.0085728},{"age":69,"percentage":0.0082555},{"age":70,"percentage":0.0084371},{"age":71,"percentage":0.0080684},{"age":72,"percentage":0.0079904},{"age":73,"percentage":0.0079921},{"age":74,"percentage":0.0080577},{"age":75,"percentage":0.0078343},{"age":76,"percentage":0.0078483},{"age":77,"percentage":0.0079290},{"age":78,"percentage":0.0080400},{"age":79,"percentage":0.0081055},{"age":80,"percentage":0.0084095},{"age":81,"percentage":0.0085257},{"age":82,"percentage":0.0087741},{"age":83,"percentage":0.0090458},{"age":84,"percentage":0.0093171},{"age":85,"percentage":0.0098787},{"age":86,"percentage":0.0101977},{"age":87,"percentage":0.0106677},{"age":88,"percentage":0.0113157},{"age":89,"percentage":0.0121885},{"age":90,"percentage":0.0137373},{"age":91,"percentage":0.0146594},{"age":92,"percentage":0.0156646},{"age":93,"percentage":0.0169234},{"age":94,"percentage":0.0181800},{"age":95,"percentage":0.0199988},{"age":96,"percentage":0.0213465},{"age":97,"percentage":0.0235418},{"age":98,"percentage":0.0256504},{"age":99,"percentage":0.0289772},{"age":100,"percentage":0.0356742},{"age":101,"percentage":0.0403860},{"age":102,"percentage":0.0423169},{"age":103,"percentage":0.0482123},{"age":104,"percentage":0.0511138},{"age":105,"percentage":0.0563975},{"age":106,"percentage":0.0610230},{"age":107,"percentage":0.0633867},{"age":108,"percentage":0.0700637},{"age":109,"percentage":0.0599190},{"age":110,"percentage":0.0719794},{"age":111,"percentage":0.0822086},{"age":112,"percentage":0.0709939},{"age":113,"percentage":0.0804954},{"age":114,"percentage":0.0759494},{"age":115,"percentage":0.1098266},{"age":116,"percentage":0.0806452},{"age":117,"percentage":0.0416667},{"age":118,"percentage":0.0967742},{"age":119,"percentage":0.0256410},{"age":120,"percentage":0.0232558}],"Venereal Diseases":[{"age":0,"percentage":0.0002133},{"age":1,"percentage":0.0002059},{"age":2,"percentage":0.0001796},{"age":3,"percentage":0.0003880},{"age":4,"percentage":0.0003579},{"age":5,"percentage":0.0003398},{"age":6,"percentage":0.0004677},{"age":7,"percentage":0.0005522},{"age":8,"percentage":0.0007394},{"age":9,"percentage":0.0007855},{"age":10,"percentage":0.0008462},{"age":11,"percentage":0.0009143},{"age":12,"percentage":0.0009123},{"age":13,"percentage":0.0006993},{"age":14,"percentage":0.0007459},{"age":15,"percentage":0.0005072},{"age":16,"percentage":0.0004869},{"age":17,"percentage":0.0004747},{"age":18,"percentage":0.0005597},{"age":19,"percentage":0.0007978},{"age":20,"percentage":0.0009319},{"age":21,"percentage":0.0014620},{"age":22,"percentage":0.0021005},{"age":23,"percentage":0.0028637},{"age":24,"percentage":0.0035523},{"age":25,"percentage":0.0043463},{"age":26,"percentage":0.0053848},{"age":27,"percentage":0.0061173},{"age":28,"percentage":0.0075862},{"age":29,"percentage":0.0084303},{"age":30,"percentage":0.0096025},{"age":31,"percentage":0.0107386},{"age":32,"percentage":0.0123023},{"age":33,"percentage":0.0135611},{"age":34,"percentage":0.0146121},{"age":35,"percentage":0.0157480},{"age":36,"percentage":0.0166912},{"age":37,"percentage":0.0174860},{"age":38,"percentage":0.0171844},{"age":39,"percentage":0.0176750},{"age":40,"percentage":0.0173410},{"age":41,"percentage":0.0168766},{"age":42,"percentage":0.0166675},{"age":43,"percentage":0.0157099},{"age":44,"percentage":0.0150760},{"age":45,"percentage":0.0136114},{"age":46,"percentage":0.0125976},{"age":47,"percentage":0.0114428},{"age":48,"percentage":0.0103127},{"age":49,"percentage":0.0091287},{"age":50,"percentage":0.0082816},{"age":51,"percentage":0.0074370},{"age":52,"percentage":0.0062245},{"age":53,"percentage":0.0055382},{"age":54,"percentage":0.0048377},{"age":55,"percentage":0.0041940},{"age":56,"percentage":0.0035141},{"age":57,"percentage":0.0030051},{"age":58,"percentage":0.0026057},{"age":59,"percentage":0.0022516},{"age":60,"percentage":0.0018157},{"age":61,"percentage":0.0015634},{"age":62,"percentage":0.0013387},{"age":63,"percentage":0.0011759},{"age":64,"percentage":0.0009816},{"age":65,"percentage":0.0008551},{"age":66,"percentage":0.0007083},{"age":67,"percentage":0.0006275},{"age":68,"percentage":0.0005736},{"age":69,"percentage":0.0004666},{"age":70,"percentage":0.0004043},{"age":71,"percentage":0.0003403},{"age":72,"percentage":0.0003052},{"age":73,"percentage":0.0002622},{"age":74,"percentage":0.0002426},{"age":75,"percentage":0.0002116},{"age":76,"percentage":0.0001775},{"age":77,"percentage":0.0001610},{"age":78,"percentage":0.0001477},{"age":79,"percentage":0.0001261},{"age":80,"percentage":0.0001014},{"age":81,"percentage":0.0000853},{"age":82,"percentage":0.0000825},{"age":83,"percentage":0.0000660},{"age":84,"percentage":0.0000595},{"age":85,"percentage":0.0000520},{"age":86,"percentage":0.0000511},{"age":87,"percentage":0.0000534},{"age":88,"percentage":0.0000405},{"age":89,"percentage":0.0000400},{"age":90,"percentage":0.0000309},{"age":91,"percentage":0.0000304},{"age":92,"percentage":0.0000256},{"age":93,"percentage":0.0000172},{"age":94,"percentage":0.0000152},{"age":95,"percentage":0.0000265},{"age":96,"percentage":0.0000264},{"age":97,"percentage":0.0000217},{"age":98,"percentage":0.0000146},{"age":99,"percentage":0.0000303},{"age":100,"percentage":0.0000380},{"age":101,"percentage":0.0000139},{"age":102,"percentage":0.0000106},{"age":103,"percentage":0.0000165},{"age":104,"percentage":0.0000000},{"age":105,"percentage":0.0000871},{"age":106,"percentage":0.0000000},{"age":107,"percentage":0.0000000},{"age":108,"percentage":0.0000000},{"age":109,"percentage":0.0000000},{"age":110,"percentage":0.0000000},{"age":111,"percentage":0.0000000},{"age":112,"percentage":0.0000000},{"age":113,"percentage":0.0000000},{"age":114,"percentage":0.0000000},{"age":115,"percentage":0.0000000},{"age":116,"percentage":0.0000000},{"age":117,"percentage":0.0000000},{"age":118,"percentage":0.0000000},{"age":119,"percentage":0.0000000},{"age":120,"percentage":0.0000000}]}
